{"assets":[{"id":"177","layers":[{"ind":176,"ty":4,"parent":175,"ks":{},"ip":0,"op":412,"st":0,"shapes":[{"ty":"rc","p":{"a":1,"k":[{"t":0,"s":[67.5,66],"i":{"x":[1,1],"y":[1,1]},"o":{"x":[0,0],"y":[0,0]}},{"t":151.62,"s":[67.5,66],"i":{"x":[0.2,0.2],"y":[1,1]},"o":{"x":[0.8,0.8],"y":[0,0]}},{"t":194.76,"s":[0,0],"i":{"x":[1,1],"y":[1,1]},"o":{"x":[0,0],"y":[0,0]}},{"t":411,"s":[0,0],"h":1}]},"r":{"a":0,"k":0},"s":{"a":1,"k":[{"t":0,"s":[135,132],"i":{"x":[1,1],"y":[1,1]},"o":{"x":[0,0],"y":[0,0]}},{"t":151.62,"s":[135,132],"i":{"x":[0.2,0.2],"y":[1,1]},"o":{"x":[0.8,0.8],"y":[0,0]}},{"t":194.76,"s":[0,0],"i":{"x":[1,1],"y":[1,1]},"o":{"x":[0,0],"y":[0,0]}},{"t":411,"s":[0,0],"h":1}]}},{"ty":"fl","c":{"a":0,"k":[0,0,0]},"o":{"a":0,"k":100}}]},{"ind":175,"ty":3,"parent":174,"ks":{"p":{"a":1,"k":[{"t":0,"s":[0,0],"i":{"x":[1,1],"y":[1,1]},"o":{"x":[0,0],"y":[0,0]}},{"t":151.62,"s":[0,0],"i":{"x":[0.2,0.2],"y":[1,1]},"o":{"x":[0.8,0.8],"y":[0,0]}},{"t":194.76,"s":[67.5,66],"i":{"x":[1,1],"y":[1,1]},"o":{"x":[0,0],"y":[0,0]}},{"t":411,"s":[67.5,66],"h":1}]}},"ip":0,"op":412,"st":0},{"ind":174,"ty":3,"ks":{"p":{"a":0,"k":[68,66]}},"ip":0,"op":412,"st":0}]},{"id":"181","layers":[{"ind":179,"ty":0,"parent":173,"ks":{"a":{"a":0,"k":[68,66]}},"w":271,"h":264,"ip":0,"op":412,"st":0,"refId":"177"},{"ind":180,"ty":4,"parent":173,"ks":{"o":{"a":1,"k":[{"t":0,"s":[100],"h":1},{"t":151.62,"s":[100],"h":1},{"t":151.62,"s":[0],"h":1},{"t":411,"s":[0],"h":1}]}},"ip":0,"op":412,"st":0,"shapes":[{"ty":"rc","p":{"a":0,"k":[88.35,73.8]},"r":{"a":0,"k":0},"s":{"a":0,"k":[206.7,177.6]}},{"ty":"fl","c":{"a":0,"k":[0,0,0]},"o":{"a":0,"k":100}}]},{"ind":173,"ty":3,"ks":{"p":{"a":0,"k":[68,66]}},"ip":0,"op":412,"st":0}]},{"id":"16","layers":[{"ind":15,"ty":4,"parent":14,"ks":{},"ip":0,"op":412,"st":0,"shapes":[{"ty":"rc","p":{"a":1,"k":[{"t":0,"s":[0,0],"i":{"x":[1,1],"y":[1,1]},"o":{"x":[0,0],"y":[0,0]}},{"t":46.86,"s":[0,0],"i":{"x":[0.966,0.966],"y":[0.957,0.957]},"o":{"x":[0.558,0.558],"y":[0,0]}},{"t":61.11,"s":[20,5],"i":{"x":[0.732,0.732],"y":[0.999,0.999]},"o":{"x":[0.394,0.394],"y":[0.787,0.787]}},{"t":64.05,"s":[19.15,4.787],"i":{"x":[0.943,0.943],"y":[0.91,0.91]},"o":{"x":[0.547,0.547],"y":[0.001,0.001]}},{"t":66.984,"s":[20,5],"i":{"x":[1,1],"y":[1,1]},"o":{"x":[0,0],"y":[0,0]}},{"t":67.59,"s":[19.963,4.991],"i":{"x":[1,1],"y":[1,1]},"o":{"x":[0,0],"y":[0,0]}},{"t":68.202,"s":[20,5],"i":{"x":[1,1],"y":[1,1]},"o":{"x":[0,0],"y":[0,0]}},{"t":411,"s":[20,5],"h":1}]},"r":{"a":0,"k":0},"s":{"a":1,"k":[{"t":0,"s":[0,0],"i":{"x":[1,1],"y":[1,1]},"o":{"x":[0,0],"y":[0,0]}},{"t":46.86,"s":[0,0],"i":{"x":[0.966,0.966],"y":[0.957,0.957]},"o":{"x":[0.558,0.558],"y":[0,0]}},{"t":61.11,"s":[40,10],"i":{"x":[0.732,0.732],"y":[0.999,0.999]},"o":{"x":[0.394,0.394],"y":[0.787,0.787]}},{"t":64.05,"s":[38.299,9.575],"i":{"x":[0.943,0.943],"y":[0.91,0.91]},"o":{"x":[0.547,0.547],"y":[0.001,0.001]}},{"t":66.984,"s":[39.999,10],"i":{"x":[1,1],"y":[1,1]},"o":{"x":[0,0],"y":[0,0]}},{"t":67.59,"s":[39.927,9.982],"i":{"x":[1,1],"y":[1,1]},"o":{"x":[0,0],"y":[0,0]}},{"t":68.202,"s":[40,10],"i":{"x":[1,1],"y":[1,1]},"o":{"x":[0,0],"y":[0,0]}},{"t":411,"s":[40,10],"h":1}]}},{"ty":"fl","c":{"a":0,"k":[0,0,0]},"o":{"a":0,"k":100}}]},{"ind":14,"ty":3,"parent":13,"ks":{},"ip":0,"op":412,"st":0},{"ind":13,"ty":3,"ks":{"p":{"a":0,"k":[20,5]}},"ip":0,"op":412,"st":0}]},{"id":"20","layers":[{"ind":18,"ty":0,"parent":12,"ks":{"a":{"a":0,"k":[20,5]}},"w":60,"h":15,"ip":0,"op":412,"st":0,"refId":"16"},{"ind":19,"ty":4,"parent":12,"ks":{"o":{"a":1,"k":[{"t":0,"s":[0],"h":1},{"t":68.46,"s":[0],"h":1},{"t":68.46,"s":[100],"h":1},{"t":411,"s":[100],"h":1}]}},"ip":0,"op":412,"st":0,"shapes":[{"ty":"rc","p":{"a":0,"k":[22,5.5]},"r":{"a":0,"k":0},"s":{"a":0,"k":[52,13]}},{"ty":"fl","c":{"a":0,"k":[0,0,0]},"o":{"a":0,"k":100}}]},{"ind":12,"ty":3,"ks":{"p":{"a":0,"k":[20,5]}},"ip":0,"op":412,"st":0}]},{"id":"9","layers":[{"ind":8,"ty":4,"parent":7,"ks":{},"ip":0,"op":412,"st":0,"shapes":[{"ty":"rc","p":{"a":0,"k":[20,5]},"r":{"a":0,"k":0},"s":{"a":0,"k":[40,10]}},{"ty":"fl","c":{"a":0,"k":[1,1,1]},"o":{"a":0,"k":100}}]},{"ind":7,"ty":3,"parent":6,"ks":{"a":{"a":0,"k":[20,5]},"p":{"a":0,"k":[20,5]},"s":{"a":1,"k":[{"t":0,"s":[120,120],"i":{"x":[1,1],"y":[1,1]},"o":{"x":[0,0],"y":[0,0]}},{"t":46.86,"s":[120,120],"i":{"x":[0.966,0.966],"y":[0.957,0.957]},"o":{"x":[0.558,0.558],"y":[0,0]}},{"t":61.11,"s":[100,100],"i":{"x":[0.732,0.732],"y":[0.999,0.999]},"o":{"x":[0.394,0.394],"y":[0.787,0.787]}},{"t":64.05,"s":[100.85,100.85],"i":{"x":[0.943,0.943],"y":[0.91,0.91]},"o":{"x":[0.547,0.547],"y":[0.001,0.001]}},{"t":66.984,"s":[100,100],"i":{"x":[1,1],"y":[1,1]},"o":{"x":[0,0],"y":[0,0]}},{"t":67.59,"s":[100.04,100.04],"i":{"x":[1,1],"y":[1,1]},"o":{"x":[0,0],"y":[0,0]}},{"t":68.202,"s":[100,100],"i":{"x":[1,1],"y":[1,1]},"o":{"x":[0,0],"y":[0,0]}},{"t":411,"s":[100,100],"h":1}]}},"ip":0,"op":412,"st":0},{"ind":6,"ty":3,"ks":{"p":{"a":0,"k":[4,1]}},"ip":0,"op":412,"st":0}]},{"id":"23","layers":[{"ind":22,"ty":0,"td":1,"parent":5,"ks":{"a":{"a":0,"k":[20,5]}},"w":80,"h":20,"ip":0,"op":412,"st":0,"refId":"20"},{"ind":11,"ty":0,"tt":1,"parent":5,"ks":{"a":{"a":0,"k":[4,1]}},"w":48,"h":12,"ip":0,"op":412,"st":0,"refId":"9"},{"ind":5,"ty":3,"ks":{"p":{"a":0,"k":[4,1]}},"ip":0,"op":412,"st":0}]},{"id":"37","layers":[{"ind":36,"ty":4,"parent":35,"ks":{},"ip":0,"op":412,"st":0,"shapes":[{"ty":"rc","p":{"a":1,"k":[{"t":0,"s":[3.5,0],"i":{"x":[1,1],"y":[1,1]},"o":{"x":[0,0],"y":[0,0]}},{"t":108.42,"s":[3.5,0],"i":{"x":[1,0.714],"y":[1,0.428]},"o":{"x":[0,0.378],"y":[0,0.001]}},{"t":120.3,"s":[3.5,5],"i":{"x":[1,0.624],"y":[1,0.999]},"o":{"x":[0,0.29],"y":[0,0.579]}},{"t":128.628,"s":[3.5,2.548],"i":{"x":[1,0.764],"y":[1,0.529]},"o":{"x":[0,0.419],"y":[0,0.001]}},{"t":136.95,"s":[3.5,4.999],"i":{"x":[1,0.688],"y":[1,0.999]},"o":{"x":[0,0.356],"y":[0,0.712]}},{"t":142.776,"s":[3.5,3.796],"i":{"x":[1,0.654],"y":[1,0.309]},"o":{"x":[0,0.323],"y":[0,0.001]}},{"t":148.602,"s":[3.5,4.999],"i":{"x":[1,0.583],"y":[1,0.998]},"o":{"x":[0,0.237],"y":[0,0.474]}},{"t":152.688,"s":[3.5,4.409],"i":{"x":[1,0.758],"y":[1,0.516]},"o":{"x":[0,0.415],"y":[0,0.002]}},{"t":156.774,"s":[3.5,5],"i":{"x":[1,0.754],"y":[1,0.999]},"o":{"x":[0,0.415],"y":[0,0.828]}},{"t":159.642,"s":[3.5,4.71],"i":{"x":[1,0.661],"y":[1,0.325]},"o":{"x":[0,0.333],"y":[0,0.003]}},{"t":162.498,"s":[3.5,5],"i":{"x":[1,0.579],"y":[1,0.996]},"o":{"x":[0,0.232],"y":[0,0.464]}},{"t":164.508,"s":[3.5,4.857],"i":{"x":[1,0.569],"y":[1,0.142]},"o":{"x":[0,0.227],"y":[0,0.002]}},{"t":166.518,"s":[3.5,5],"i":{"x":[1,0.596],"y":[1,0.993]},"o":{"x":[0,0.26],"y":[0,0.517]}},{"t":167.928,"s":[3.5,4.93],"i":{"x":[1,0.921],"y":[1,0.841]},"o":{"x":[0,0.515],"y":[0,0.006]}},{"t":169.344,"s":[3.5,5],"i":{"x":[1,0.652],"y":[1,0.995]},"o":{"x":[0,0.336],"y":[0,0.666]}},{"t":170.334,"s":[3.5,4.965],"i":{"x":[1,0.95],"y":[1,0.9]},"o":{"x":[0,0.531],"y":[0,0.014]}},{"t":171.33,"s":[3.5,5],"i":{"x":[1,0.65],"y":[1,0.99]},"o":{"x":[0,0.342],"y":[0,0.673]}},{"t":172.02,"s":[3.5,4.983],"i":{"x":[1,0.974],"y":[1,0.948]},"o":{"x":[0,0.545],"y":[0,0.015]}},{"t":172.722,"s":[3.5,5],"i":{"x":[1,1],"y":[1,1]},"o":{"x":[0,0],"y":[0,0]}},{"t":173.214,"s":[3.5,4.991],"i":{"x":[1,1],"y":[1,1]},"o":{"x":[0,0],"y":[0,0]}},{"t":173.706,"s":[3.5,5],"i":{"x":[1,1],"y":[1,1]},"o":{"x":[0,0],"y":[0,0]}},{"t":411,"s":[3.5,5],"h":1}]},"r":{"a":0,"k":0},"s":{"a":1,"k":[{"t":0,"s":[7,0],"i":{"x":[1,1],"y":[1,1]},"o":{"x":[0,0],"y":[0,0]}},{"t":108.42,"s":[7,0],"i":{"x":[1,0.714],"y":[1,0.428]},"o":{"x":[0,0.378],"y":[0,0.001]}},{"t":120.3,"s":[7,10],"i":{"x":[1,0.624],"y":[1,0.999]},"o":{"x":[0,0.29],"y":[0,0.579]}},{"t":128.628,"s":[7,5.095],"i":{"x":[1,0.764],"y":[1,0.529]},"o":{"x":[0,0.419],"y":[0,0.001]}},{"t":136.95,"s":[7,9.998],"i":{"x":[1,0.688],"y":[1,0.999]},"o":{"x":[0,0.356],"y":[0,0.712]}},{"t":142.776,"s":[7,7.593],"i":{"x":[1,0.654],"y":[1,0.309]},"o":{"x":[0,0.323],"y":[0,0.001]}},{"t":148.602,"s":[7,9.999],"i":{"x":[1,0.583],"y":[1,0.998]},"o":{"x":[0,0.237],"y":[0,0.474]}},{"t":152.688,"s":[7,8.818],"i":{"x":[1,0.758],"y":[1,0.516]},"o":{"x":[0,0.415],"y":[0,0.002]}},{"t":156.774,"s":[7,10],"i":{"x":[1,0.754],"y":[1,0.999]},"o":{"x":[0,0.415],"y":[0,0.828]}},{"t":159.642,"s":[7,9.419],"i":{"x":[1,0.661],"y":[1,0.325]},"o":{"x":[0,0.333],"y":[0,0.003]}},{"t":162.498,"s":[7,9.999],"i":{"x":[1,0.579],"y":[1,0.996]},"o":{"x":[0,0.232],"y":[0,0.464]}},{"t":164.508,"s":[7,9.714],"i":{"x":[1,0.569],"y":[1,0.142]},"o":{"x":[0,0.227],"y":[0,0.002]}},{"t":166.518,"s":[7,10],"i":{"x":[1,0.596],"y":[1,0.993]},"o":{"x":[0,0.26],"y":[0,0.517]}},{"t":167.928,"s":[7,9.859],"i":{"x":[1,0.921],"y":[1,0.841]},"o":{"x":[0,0.515],"y":[0,0.006]}},{"t":169.344,"s":[7,10],"i":{"x":[1,0.652],"y":[1,0.995]},"o":{"x":[0,0.336],"y":[0,0.666]}},{"t":170.334,"s":[7,9.93],"i":{"x":[1,0.95],"y":[1,0.9]},"o":{"x":[0,0.531],"y":[0,0.014]}},{"t":171.33,"s":[7,10],"i":{"x":[1,0.65],"y":[1,0.99]},"o":{"x":[0,0.342],"y":[0,0.673]}},{"t":172.02,"s":[7,9.965],"i":{"x":[1,0.974],"y":[1,0.948]},"o":{"x":[0,0.545],"y":[0,0.015]}},{"t":172.722,"s":[7,10],"i":{"x":[1,1],"y":[1,1]},"o":{"x":[0,0],"y":[0,0]}},{"t":173.214,"s":[7,9.983],"i":{"x":[1,1],"y":[1,1]},"o":{"x":[0,0],"y":[0,0]}},{"t":173.706,"s":[7,10],"i":{"x":[1,1],"y":[1,1]},"o":{"x":[0,0],"y":[0,0]}},{"t":411,"s":[7,10],"h":1}]}},{"ty":"fl","c":{"a":0,"k":[0,0,0]},"o":{"a":0,"k":100}}]},{"ind":35,"ty":3,"parent":34,"ks":{"p":{"a":1,"k":[{"t":0,"s":[0,10],"i":{"x":[1,1],"y":[1,1]},"o":{"x":[0,0],"y":[0,0]}},{"t":108.42,"s":[0,10],"i":{"x":[1,0.714],"y":[1,0.428]},"o":{"x":[0,0.378],"y":[0,0.001]}},{"t":120.3,"s":[0,0],"i":{"x":[1,0.624],"y":[1,0.999]},"o":{"x":[0,0.29],"y":[0,0.579]}},{"t":128.628,"s":[0,4.905],"i":{"x":[1,0.764],"y":[1,0.529]},"o":{"x":[0,0.419],"y":[0,0.001]}},{"t":136.95,"s":[0,0.002],"i":{"x":[1,0.688],"y":[1,0.999]},"o":{"x":[0,0.356],"y":[0,0.712]}},{"t":142.776,"s":[0,2.407],"i":{"x":[1,0.654],"y":[1,0.309]},"o":{"x":[0,0.323],"y":[0,0.001]}},{"t":148.602,"s":[0,0.001],"i":{"x":[1,0.583],"y":[1,0.998]},"o":{"x":[0,0.237],"y":[0,0.474]}},{"t":152.688,"s":[0,1.182],"i":{"x":[1,0.758],"y":[1,0.516]},"o":{"x":[0,0.415],"y":[0,0.002]}},{"t":156.774,"s":[0,0],"i":{"x":[1,0.754],"y":[1,0.999]},"o":{"x":[0,0.415],"y":[0,0.828]}},{"t":159.642,"s":[0,0.581],"i":{"x":[1,0.661],"y":[1,0.325]},"o":{"x":[0,0.333],"y":[0,0.003]}},{"t":162.498,"s":[0,0.001],"i":{"x":[1,0.579],"y":[1,0.996]},"o":{"x":[0,0.232],"y":[0,0.464]}},{"t":164.508,"s":[0,0.286],"i":{"x":[1,0.569],"y":[1,0.142]},"o":{"x":[0,0.227],"y":[0,0.002]}},{"t":166.518,"s":[0,0],"i":{"x":[1,0.596],"y":[1,0.993]},"o":{"x":[0,0.26],"y":[0,0.517]}},{"t":167.928,"s":[0,0.141],"i":{"x":[1,0.921],"y":[1,0.841]},"o":{"x":[0,0.515],"y":[0,0.006]}},{"t":169.344,"s":[0,0],"i":{"x":[1,0.652],"y":[1,0.995]},"o":{"x":[0,0.336],"y":[0,0.666]}},{"t":170.334,"s":[0,0.07],"i":{"x":[1,0.95],"y":[1,0.9]},"o":{"x":[0,0.531],"y":[0,0.014]}},{"t":171.33,"s":[0,0],"i":{"x":[1,0.65],"y":[1,0.99]},"o":{"x":[0,0.342],"y":[0,0.673]}},{"t":172.02,"s":[0,0.035],"i":{"x":[1,0.974],"y":[1,0.948]},"o":{"x":[0,0.545],"y":[0,0.015]}},{"t":172.722,"s":[0,0],"i":{"x":[1,1],"y":[1,1]},"o":{"x":[0,0],"y":[0,0]}},{"t":173.214,"s":[0,0.017],"i":{"x":[1,1],"y":[1,1]},"o":{"x":[0,0],"y":[0,0]}},{"t":173.706,"s":[0,0],"i":{"x":[1,1],"y":[1,1]},"o":{"x":[0,0],"y":[0,0]}},{"t":411,"s":[0,0],"h":1}]}},"ip":0,"op":412,"st":0},{"ind":34,"ty":3,"ks":{"p":{"a":0,"k":[0,5]}},"ip":0,"op":412,"st":0}]},{"id":"41","layers":[{"ind":39,"ty":0,"parent":33,"ks":{"a":{"a":0,"k":[0,5]}},"w":7,"h":25,"ip":0,"op":412,"st":0,"refId":"37"},{"ind":40,"ty":4,"parent":33,"ks":{"o":{"a":1,"k":[{"t":0,"s":[0],"h":1},{"t":175.86,"s":[0],"h":1},{"t":175.86,"s":[100],"h":1},{"t":411,"s":[100],"h":1}]}},"ip":0,"op":412,"st":0,"shapes":[{"ty":"rc","p":{"a":0,"k":[3.85,5.5]},"r":{"a":0,"k":0},"s":{"a":0,"k":[9.7,13]}},{"ty":"fl","c":{"a":0,"k":[0,0,0]},"o":{"a":0,"k":100}}]},{"ind":33,"ty":3,"ks":{"p":{"a":0,"k":[1,5]}},"ip":0,"op":412,"st":0}]},{"id":"30","layers":[{"ind":29,"ty":4,"parent":28,"ks":{},"ip":0,"op":412,"st":0,"shapes":[{"ty":"rc","p":{"a":0,"k":[3.5,5]},"r":{"a":0,"k":0},"s":{"a":0,"k":[7,10]}},{"ty":"fl","c":{"a":0,"k":[1,1,1]},"o":{"a":0,"k":100}}]},{"ind":28,"ty":3,"parent":27,"ks":{"a":{"a":0,"k":[3.5,5]},"p":{"a":0,"k":[3.5,5]},"s":{"a":1,"k":[{"t":0,"s":[120,120],"i":{"x":[1,1],"y":[1,1]},"o":{"x":[0,0],"y":[0,0]}},{"t":108.42,"s":[120,120],"i":{"x":[0.714,0.714],"y":[0.428,0.428]},"o":{"x":[0.378,0.378],"y":[0.001,0.001]}},{"t":120.3,"s":[100,100],"i":{"x":[0.624,0.624],"y":[0.999,0.999]},"o":{"x":[0.29,0.29],"y":[0.579,0.579]}},{"t":128.628,"s":[109.81,109.81],"i":{"x":[0.764,0.764],"y":[0.529,0.529]},"o":{"x":[0.419,0.419],"y":[0.001,0.001]}},{"t":136.95,"s":[100,100],"i":{"x":[0.688,0.688],"y":[0.999,0.999]},"o":{"x":[0.356,0.356],"y":[0.712,0.712]}},{"t":142.776,"s":[104.81,104.81],"i":{"x":[0.654,0.654],"y":[0.309,0.309]},"o":{"x":[0.323,0.323],"y":[0.001,0.001]}},{"t":148.602,"s":[100,100],"i":{"x":[0.583,0.583],"y":[0.998,0.998]},"o":{"x":[0.237,0.237],"y":[0.474,0.474]}},{"t":152.688,"s":[102.36,102.36],"i":{"x":[0.758,0.758],"y":[0.516,0.516]},"o":{"x":[0.415,0.415],"y":[0.002,0.002]}},{"t":156.774,"s":[100,100],"i":{"x":[0.754,0.754],"y":[0.999,0.999]},"o":{"x":[0.415,0.415],"y":[0.828,0.828]}},{"t":159.642,"s":[101.16,101.16],"i":{"x":[0.661,0.661],"y":[0.325,0.325]},"o":{"x":[0.333,0.333],"y":[0.003,0.003]}},{"t":162.498,"s":[100,100],"i":{"x":[0.579,0.579],"y":[0.996,0.996]},"o":{"x":[0.232,0.232],"y":[0.464,0.464]}},{"t":164.508,"s":[100.57,100.57],"i":{"x":[0.569,0.569],"y":[0.142,0.142]},"o":{"x":[0.227,0.227],"y":[0.002,0.002]}},{"t":166.518,"s":[100,100],"i":{"x":[0.596,0.596],"y":[0.993,0.993]},"o":{"x":[0.26,0.26],"y":[0.517,0.517]}},{"t":167.928,"s":[100.28,100.28],"i":{"x":[0.921,0.921],"y":[0.841,0.841]},"o":{"x":[0.515,0.515],"y":[0.006,0.006]}},{"t":169.344,"s":[100,100],"i":{"x":[0.652,0.652],"y":[0.995,0.995]},"o":{"x":[0.336,0.336],"y":[0.666,0.666]}},{"t":170.334,"s":[100.14,100.14],"i":{"x":[0.95,0.95],"y":[0.9,0.9]},"o":{"x":[0.531,0.531],"y":[0.014,0.014]}},{"t":171.33,"s":[100,100],"i":{"x":[0.65,0.65],"y":[0.99,0.99]},"o":{"x":[0.342,0.342],"y":[0.673,0.673]}},{"t":172.02,"s":[100.07,100.07],"i":{"x":[0.974,0.974],"y":[0.948,0.948]},"o":{"x":[0.545,0.545],"y":[0.015,0.015]}},{"t":172.722,"s":[100,100],"i":{"x":[1,1],"y":[1,1]},"o":{"x":[0,0],"y":[0,0]}},{"t":173.214,"s":[100.03,100.03],"i":{"x":[1,1],"y":[1,1]},"o":{"x":[0,0],"y":[0,0]}},{"t":173.706,"s":[100,100],"i":{"x":[1,1],"y":[1,1]},"o":{"x":[0,0],"y":[0,0]}},{"t":411,"s":[100,100],"h":1}]}},"ip":0,"op":412,"st":0},{"ind":27,"ty":3,"ks":{"p":{"a":0,"k":[1,1]}},"ip":0,"op":412,"st":0}]},{"id":"44","layers":[{"ind":43,"ty":0,"td":1,"parent":26,"ks":{"a":{"a":0,"k":[1,5]}},"w":10,"h":30,"ip":0,"op":412,"st":0,"refId":"41"},{"ind":32,"ty":0,"tt":1,"parent":26,"ks":{"a":{"a":0,"k":[1,1]}},"w":9,"h":12,"ip":0,"op":412,"st":0,"refId":"30"},{"ind":26,"ty":3,"ks":{"p":{"a":0,"k":[1,1]}},"ip":0,"op":412,"st":0}]},{"id":"58","layers":[{"ind":57,"ty":4,"parent":56,"ks":{},"ip":0,"op":412,"st":0,"shapes":[{"ty":"rc","p":{"a":1,"k":[{"t":0,"s":[0,0],"i":{"x":[1,1],"y":[1,1]},"o":{"x":[0,0],"y":[0,0]}},{"t":95.82,"s":[0,0],"i":{"x":[0.966,0.966],"y":[0.957,0.957]},"o":{"x":[0.558,0.558],"y":[0,0]}},{"t":104.094,"s":[45,5],"i":{"x":[0.732,0.732],"y":[0.999,0.999]},"o":{"x":[0.394,0.394],"y":[0.787,0.787]}},{"t":105.798,"s":[43.087,4.787],"i":{"x":[0.943,0.943],"y":[0.91,0.91]},"o":{"x":[0.547,0.547],"y":[0.001,0.001]}},{"t":107.502,"s":[44.999,5],"i":{"x":[1,1],"y":[1,1]},"o":{"x":[0,0],"y":[0,0]}},{"t":107.856,"s":[44.918,4.991],"i":{"x":[1,1],"y":[1,1]},"o":{"x":[0,0],"y":[0,0]}},{"t":108.21,"s":[45,5],"i":{"x":[1,1],"y":[1,1]},"o":{"x":[0,0],"y":[0,0]}},{"t":411,"s":[45,5],"h":1}]},"r":{"a":0,"k":0},"s":{"a":1,"k":[{"t":0,"s":[0,0],"i":{"x":[1,1],"y":[1,1]},"o":{"x":[0,0],"y":[0,0]}},{"t":95.82,"s":[0,0],"i":{"x":[0.966,0.966],"y":[0.957,0.957]},"o":{"x":[0.558,0.558],"y":[0,0]}},{"t":104.094,"s":[90,10],"i":{"x":[0.732,0.732],"y":[0.999,0.999]},"o":{"x":[0.394,0.394],"y":[0.787,0.787]}},{"t":105.798,"s":[86.174,9.575],"i":{"x":[0.943,0.943],"y":[0.91,0.91]},"o":{"x":[0.547,0.547],"y":[0.001,0.001]}},{"t":107.502,"s":[89.998,10],"i":{"x":[1,1],"y":[1,1]},"o":{"x":[0,0],"y":[0,0]}},{"t":107.856,"s":[89.835,9.982],"i":{"x":[1,1],"y":[1,1]},"o":{"x":[0,0],"y":[0,0]}},{"t":108.21,"s":[90,10],"i":{"x":[1,1],"y":[1,1]},"o":{"x":[0,0],"y":[0,0]}},{"t":411,"s":[90,10],"h":1}]}},{"ty":"fl","c":{"a":0,"k":[0,0,0]},"o":{"a":0,"k":100}}]},{"ind":56,"ty":3,"parent":55,"ks":{},"ip":0,"op":412,"st":0},{"ind":55,"ty":3,"ks":{"p":{"a":0,"k":[45,5]}},"ip":0,"op":412,"st":0}]},{"id":"62","layers":[{"ind":60,"ty":0,"parent":54,"ks":{"a":{"a":0,"k":[45,5]}},"w":135,"h":15,"ip":0,"op":412,"st":0,"refId":"58"},{"ind":61,"ty":4,"parent":54,"ks":{"o":{"a":1,"k":[{"t":0,"s":[0],"h":1},{"t":108.36,"s":[0],"h":1},{"t":108.36,"s":[100],"h":1},{"t":411,"s":[100],"h":1}]}},"ip":0,"op":412,"st":0,"shapes":[{"ty":"rc","p":{"a":0,"k":[49.5,5.5]},"r":{"a":0,"k":0},"s":{"a":0,"k":[117,13]}},{"ty":"fl","c":{"a":0,"k":[0,0,0]},"o":{"a":0,"k":100}}]},{"ind":54,"ty":3,"ks":{"p":{"a":0,"k":[45,5]}},"ip":0,"op":412,"st":0}]},{"id":"51","layers":[{"ind":50,"ty":4,"parent":49,"ks":{},"ip":0,"op":412,"st":0,"shapes":[{"ty":"rc","p":{"a":0,"k":[45,5]},"r":{"a":0,"k":0},"s":{"a":0,"k":[90,10]}},{"ty":"fl","c":{"a":0,"k":[1,1,1]},"o":{"a":0,"k":100}}]},{"ind":49,"ty":3,"parent":48,"ks":{"a":{"a":0,"k":[45,5]},"p":{"a":0,"k":[45,5]},"s":{"a":1,"k":[{"t":0,"s":[120,120],"i":{"x":[1,1],"y":[1,1]},"o":{"x":[0,0],"y":[0,0]}},{"t":95.82,"s":[120,120],"i":{"x":[0.966,0.966],"y":[0.957,0.957]},"o":{"x":[0.558,0.558],"y":[0,0]}},{"t":104.094,"s":[100,100],"i":{"x":[0.732,0.732],"y":[0.999,0.999]},"o":{"x":[0.394,0.394],"y":[0.787,0.787]}},{"t":105.798,"s":[100.85,100.85],"i":{"x":[0.943,0.943],"y":[0.91,0.91]},"o":{"x":[0.547,0.547],"y":[0.001,0.001]}},{"t":107.502,"s":[100,100],"i":{"x":[1,1],"y":[1,1]},"o":{"x":[0,0],"y":[0,0]}},{"t":107.856,"s":[100.04,100.04],"i":{"x":[1,1],"y":[1,1]},"o":{"x":[0,0],"y":[0,0]}},{"t":108.21,"s":[100,100],"i":{"x":[1,1],"y":[1,1]},"o":{"x":[0,0],"y":[0,0]}},{"t":411,"s":[100,100],"h":1}]}},"ip":0,"op":412,"st":0},{"ind":48,"ty":3,"ks":{"p":{"a":0,"k":[9,1]}},"ip":0,"op":412,"st":0}]},{"id":"65","layers":[{"ind":64,"ty":0,"td":1,"parent":47,"ks":{"a":{"a":0,"k":[45,5]}},"w":180,"h":20,"ip":0,"op":412,"st":0,"refId":"62"},{"ind":53,"ty":0,"tt":1,"parent":47,"ks":{"a":{"a":0,"k":[9,1]}},"w":108,"h":12,"ip":0,"op":412,"st":0,"refId":"51"},{"ind":47,"ty":3,"ks":{"p":{"a":0,"k":[9,1]}},"ip":0,"op":412,"st":0}]},{"id":"79","layers":[{"ind":78,"ty":4,"parent":77,"ks":{},"ip":0,"op":412,"st":0,"shapes":[{"ty":"rc","p":{"a":1,"k":[{"t":0,"s":[0,0],"i":{"x":[1,1],"y":[1,1]},"o":{"x":[0,0],"y":[0,0]}},{"t":84.54,"s":[0,0],"i":{"x":[0.966,0.966],"y":[0.957,0.957]},"o":{"x":[0.558,0.558],"y":[0,0]}},{"t":93.96,"s":[57.5,5],"i":{"x":[0.732,0.732],"y":[0.999,0.999]},"o":{"x":[0.394,0.394],"y":[0.787,0.787]}},{"t":95.904,"s":[55.056,4.787],"i":{"x":[0.943,0.943],"y":[0.91,0.91]},"o":{"x":[0.547,0.547],"y":[0.001,0.001]}},{"t":97.842,"s":[57.499,5],"i":{"x":[1,1],"y":[1,1]},"o":{"x":[0,0],"y":[0,0]}},{"t":98.244,"s":[57.395,4.991],"i":{"x":[1,1],"y":[1,1]},"o":{"x":[0,0],"y":[0,0]}},{"t":98.652,"s":[57.5,5],"i":{"x":[1,1],"y":[1,1]},"o":{"x":[0,0],"y":[0,0]}},{"t":411,"s":[57.5,5],"h":1}]},"r":{"a":0,"k":0},"s":{"a":1,"k":[{"t":0,"s":[0,0],"i":{"x":[1,1],"y":[1,1]},"o":{"x":[0,0],"y":[0,0]}},{"t":84.54,"s":[0,0],"i":{"x":[0.966,0.966],"y":[0.957,0.957]},"o":{"x":[0.558,0.558],"y":[0,0]}},{"t":93.96,"s":[114.999,10],"i":{"x":[0.732,0.732],"y":[0.999,0.999]},"o":{"x":[0.394,0.394],"y":[0.787,0.787]}},{"t":95.904,"s":[110.111,9.575],"i":{"x":[0.943,0.943],"y":[0.91,0.91]},"o":{"x":[0.547,0.547],"y":[0.001,0.001]}},{"t":97.842,"s":[114.998,10],"i":{"x":[1,1],"y":[1,1]},"o":{"x":[0,0],"y":[0,0]}},{"t":98.244,"s":[114.789,9.982],"i":{"x":[1,1],"y":[1,1]},"o":{"x":[0,0],"y":[0,0]}},{"t":98.652,"s":[114.999,10],"i":{"x":[1,1],"y":[1,1]},"o":{"x":[0,0],"y":[0,0]}},{"t":98.82,"s":[115,10],"i":{"x":[1,1],"y":[1,1]},"o":{"x":[0,0],"y":[0,0]}},{"t":411,"s":[115,10],"h":1}]}},{"ty":"fl","c":{"a":0,"k":[0,0,0]},"o":{"a":0,"k":100}}]},{"ind":77,"ty":3,"parent":76,"ks":{},"ip":0,"op":412,"st":0},{"ind":76,"ty":3,"ks":{"p":{"a":0,"k":[58,5]}},"ip":0,"op":412,"st":0}]},{"id":"83","layers":[{"ind":81,"ty":0,"parent":75,"ks":{"a":{"a":0,"k":[58,5]}},"w":173,"h":15,"ip":0,"op":412,"st":0,"refId":"79"},{"ind":82,"ty":4,"parent":75,"ks":{"o":{"a":1,"k":[{"t":0,"s":[0],"h":1},{"t":98.82,"s":[0],"h":1},{"t":98.82,"s":[100],"h":1},{"t":411,"s":[100],"h":1}]}},"ip":0,"op":412,"st":0,"shapes":[{"ty":"rc","p":{"a":0,"k":[63.25,5.5]},"r":{"a":0,"k":0},"s":{"a":0,"k":[150.5,13]}},{"ty":"fl","c":{"a":0,"k":[0,0,0]},"o":{"a":0,"k":100}}]},{"ind":75,"ty":3,"ks":{"p":{"a":0,"k":[58,5]}},"ip":0,"op":412,"st":0}]},{"id":"72","layers":[{"ind":71,"ty":4,"parent":70,"ks":{},"ip":0,"op":412,"st":0,"shapes":[{"ty":"rc","p":{"a":0,"k":[57.5,5]},"r":{"a":0,"k":0},"s":{"a":0,"k":[115,10]}},{"ty":"fl","c":{"a":0,"k":[1,1,1]},"o":{"a":0,"k":100}}]},{"ind":70,"ty":3,"parent":69,"ks":{"a":{"a":0,"k":[57.5,5]},"p":{"a":0,"k":[57.5,5]},"s":{"a":1,"k":[{"t":0,"s":[120,120],"i":{"x":[1,1],"y":[1,1]},"o":{"x":[0,0],"y":[0,0]}},{"t":84.54,"s":[120,120],"i":{"x":[0.966,0.966],"y":[0.957,0.957]},"o":{"x":[0.558,0.558],"y":[0,0]}},{"t":93.96,"s":[100,100],"i":{"x":[0.732,0.732],"y":[0.999,0.999]},"o":{"x":[0.394,0.394],"y":[0.787,0.787]}},{"t":95.904,"s":[100.85,100.85],"i":{"x":[0.943,0.943],"y":[0.91,0.91]},"o":{"x":[0.547,0.547],"y":[0.001,0.001]}},{"t":97.842,"s":[100,100],"i":{"x":[1,1],"y":[1,1]},"o":{"x":[0,0],"y":[0,0]}},{"t":98.244,"s":[100.04,100.04],"i":{"x":[1,1],"y":[1,1]},"o":{"x":[0,0],"y":[0,0]}},{"t":98.652,"s":[100,100],"i":{"x":[1,1],"y":[1,1]},"o":{"x":[0,0],"y":[0,0]}},{"t":411,"s":[100,100],"h":1}]}},"ip":0,"op":412,"st":0},{"ind":69,"ty":3,"ks":{"p":{"a":0,"k":[12,1]}},"ip":0,"op":412,"st":0}]},{"id":"86","layers":[{"ind":85,"ty":0,"td":1,"parent":68,"ks":{"a":{"a":0,"k":[58,5]}},"w":231,"h":20,"ip":0,"op":412,"st":0,"refId":"83"},{"ind":74,"ty":0,"tt":1,"parent":68,"ks":{"a":{"a":0,"k":[12,1]}},"w":139,"h":12,"ip":0,"op":412,"st":0,"refId":"72"},{"ind":68,"ty":3,"ks":{"p":{"a":0,"k":[12,1]}},"ip":0,"op":412,"st":0}]},{"id":"100","layers":[{"ind":99,"ty":4,"parent":98,"ks":{},"ip":0,"op":412,"st":0,"shapes":[{"ty":"rc","p":{"a":1,"k":[{"t":0,"s":[0,0],"i":{"x":[1,1],"y":[1,1]},"o":{"x":[0,0],"y":[0,0]}},{"t":69.3,"s":[0,0],"i":{"x":[0.966,0.966],"y":[0.957,0.957]},"o":{"x":[0.558,0.558],"y":[0,0]}},{"t":82.998,"s":[57.5,5],"i":{"x":[0.732,0.732],"y":[0.999,0.999]},"o":{"x":[0.394,0.394],"y":[0.787,0.787]}},{"t":85.818,"s":[55.056,4.787],"i":{"x":[0.943,0.943],"y":[0.91,0.91]},"o":{"x":[0.547,0.547],"y":[0.001,0.001]}},{"t":88.644,"s":[57.499,5],"i":{"x":[1,1],"y":[1,1]},"o":{"x":[0,0],"y":[0,0]}},{"t":89.226,"s":[57.395,4.991],"i":{"x":[1,1],"y":[1,1]},"o":{"x":[0,0],"y":[0,0]}},{"t":89.814,"s":[57.5,5],"i":{"x":[1,1],"y":[1,1]},"o":{"x":[0,0],"y":[0,0]}},{"t":411,"s":[57.5,5],"h":1}]},"r":{"a":0,"k":0},"s":{"a":1,"k":[{"t":0,"s":[0,0],"i":{"x":[1,1],"y":[1,1]},"o":{"x":[0,0],"y":[0,0]}},{"t":69.3,"s":[0,0],"i":{"x":[0.966,0.966],"y":[0.957,0.957]},"o":{"x":[0.558,0.558],"y":[0,0]}},{"t":82.998,"s":[114.999,10],"i":{"x":[0.732,0.732],"y":[0.999,0.999]},"o":{"x":[0.394,0.394],"y":[0.787,0.787]}},{"t":85.818,"s":[110.111,9.575],"i":{"x":[0.943,0.943],"y":[0.91,0.91]},"o":{"x":[0.547,0.547],"y":[0.001,0.001]}},{"t":88.644,"s":[114.998,10],"i":{"x":[1,1],"y":[1,1]},"o":{"x":[0,0],"y":[0,0]}},{"t":89.226,"s":[114.789,9.982],"i":{"x":[1,1],"y":[1,1]},"o":{"x":[0,0],"y":[0,0]}},{"t":89.814,"s":[114.999,10],"i":{"x":[1,1],"y":[1,1]},"o":{"x":[0,0],"y":[0,0]}},{"t":90.06,"s":[115,10],"i":{"x":[1,1],"y":[1,1]},"o":{"x":[0,0],"y":[0,0]}},{"t":411,"s":[115,10],"h":1}]}},{"ty":"fl","c":{"a":0,"k":[0,0,0]},"o":{"a":0,"k":100}}]},{"ind":98,"ty":3,"parent":97,"ks":{},"ip":0,"op":412,"st":0},{"ind":97,"ty":3,"ks":{"p":{"a":0,"k":[58,5]}},"ip":0,"op":412,"st":0}]},{"id":"104","layers":[{"ind":102,"ty":0,"parent":96,"ks":{"a":{"a":0,"k":[58,5]}},"w":173,"h":15,"ip":0,"op":412,"st":0,"refId":"100"},{"ind":103,"ty":4,"parent":96,"ks":{"o":{"a":1,"k":[{"t":0,"s":[0],"h":1},{"t":90.06,"s":[0],"h":1},{"t":90.06,"s":[100],"h":1},{"t":411,"s":[100],"h":1}]}},"ip":0,"op":412,"st":0,"shapes":[{"ty":"rc","p":{"a":0,"k":[63.25,5.5]},"r":{"a":0,"k":0},"s":{"a":0,"k":[150.5,13]}},{"ty":"fl","c":{"a":0,"k":[0,0,0]},"o":{"a":0,"k":100}}]},{"ind":96,"ty":3,"ks":{"p":{"a":0,"k":[58,5]}},"ip":0,"op":412,"st":0}]},{"id":"93","layers":[{"ind":92,"ty":4,"parent":91,"ks":{},"ip":0,"op":412,"st":0,"shapes":[{"ty":"rc","p":{"a":0,"k":[57.5,5]},"r":{"a":0,"k":0},"s":{"a":0,"k":[115,10]}},{"ty":"fl","c":{"a":0,"k":[1,1,1]},"o":{"a":0,"k":100}}]},{"ind":91,"ty":3,"parent":90,"ks":{"a":{"a":0,"k":[57.5,5]},"p":{"a":0,"k":[57.5,5]},"s":{"a":1,"k":[{"t":0,"s":[120,120],"i":{"x":[1,1],"y":[1,1]},"o":{"x":[0,0],"y":[0,0]}},{"t":69.3,"s":[120,120],"i":{"x":[0.966,0.966],"y":[0.957,0.957]},"o":{"x":[0.558,0.558],"y":[0,0]}},{"t":82.998,"s":[100,100],"i":{"x":[0.732,0.732],"y":[0.999,0.999]},"o":{"x":[0.394,0.394],"y":[0.787,0.787]}},{"t":85.818,"s":[100.85,100.85],"i":{"x":[0.943,0.943],"y":[0.91,0.91]},"o":{"x":[0.547,0.547],"y":[0.001,0.001]}},{"t":88.644,"s":[100,100],"i":{"x":[1,1],"y":[1,1]},"o":{"x":[0,0],"y":[0,0]}},{"t":89.226,"s":[100.04,100.04],"i":{"x":[1,1],"y":[1,1]},"o":{"x":[0,0],"y":[0,0]}},{"t":89.814,"s":[100,100],"i":{"x":[1,1],"y":[1,1]},"o":{"x":[0,0],"y":[0,0]}},{"t":411,"s":[100,100],"h":1}]}},"ip":0,"op":412,"st":0},{"ind":90,"ty":3,"ks":{"p":{"a":0,"k":[12,1]}},"ip":0,"op":412,"st":0}]},{"id":"107","layers":[{"ind":106,"ty":0,"td":1,"parent":89,"ks":{"a":{"a":0,"k":[58,5]}},"w":231,"h":20,"ip":0,"op":412,"st":0,"refId":"104"},{"ind":95,"ty":0,"tt":1,"parent":89,"ks":{"a":{"a":0,"k":[12,1]}},"w":139,"h":12,"ip":0,"op":412,"st":0,"refId":"93"},{"ind":89,"ty":3,"ks":{"p":{"a":0,"k":[12,1]}},"ip":0,"op":412,"st":0}]},{"id":"121","layers":[{"ind":120,"ty":4,"parent":119,"ks":{},"ip":0,"op":412,"st":0,"shapes":[{"ty":"rc","p":{"a":1,"k":[{"t":0,"s":[0,0],"i":{"x":[1,1],"y":[1,1]},"o":{"x":[0,0],"y":[0,0]}},{"t":62.82,"s":[0,0],"i":{"x":[0.966,0.966],"y":[0.957,0.957]},"o":{"x":[0.558,0.558],"y":[0,0]}},{"t":73.35,"s":[57.5,5],"i":{"x":[0.732,0.732],"y":[0.999,0.999]},"o":{"x":[0.394,0.394],"y":[0.787,0.787]}},{"t":75.522,"s":[55.056,4.787],"i":{"x":[0.943,0.943],"y":[0.91,0.91]},"o":{"x":[0.547,0.547],"y":[0.001,0.001]}},{"t":77.688,"s":[57.499,5],"i":{"x":[1,1],"y":[1,1]},"o":{"x":[0,0],"y":[0,0]}},{"t":78.138,"s":[57.395,4.991],"i":{"x":[1,1],"y":[1,1]},"o":{"x":[0,0],"y":[0,0]}},{"t":78.588,"s":[57.5,5],"i":{"x":[1,1],"y":[1,1]},"o":{"x":[0,0],"y":[0,0]}},{"t":411,"s":[57.5,5],"h":1}]},"r":{"a":0,"k":0},"s":{"a":1,"k":[{"t":0,"s":[0,0],"i":{"x":[1,1],"y":[1,1]},"o":{"x":[0,0],"y":[0,0]}},{"t":62.82,"s":[0,0],"i":{"x":[0.966,0.966],"y":[0.957,0.957]},"o":{"x":[0.558,0.558],"y":[0,0]}},{"t":73.35,"s":[114.999,10],"i":{"x":[0.732,0.732],"y":[0.999,0.999]},"o":{"x":[0.394,0.394],"y":[0.787,0.787]}},{"t":75.522,"s":[110.111,9.575],"i":{"x":[0.943,0.943],"y":[0.91,0.91]},"o":{"x":[0.547,0.547],"y":[0.001,0.001]}},{"t":77.688,"s":[114.998,10],"i":{"x":[1,1],"y":[1,1]},"o":{"x":[0,0],"y":[0,0]}},{"t":78.138,"s":[114.789,9.982],"i":{"x":[1,1],"y":[1,1]},"o":{"x":[0,0],"y":[0,0]}},{"t":78.588,"s":[114.999,10],"i":{"x":[1,1],"y":[1,1]},"o":{"x":[0,0],"y":[0,0]}},{"t":78.78,"s":[115,10],"i":{"x":[1,1],"y":[1,1]},"o":{"x":[0,0],"y":[0,0]}},{"t":411,"s":[115,10],"h":1}]}},{"ty":"fl","c":{"a":0,"k":[0,0,0]},"o":{"a":0,"k":100}}]},{"ind":119,"ty":3,"parent":118,"ks":{},"ip":0,"op":412,"st":0},{"ind":118,"ty":3,"ks":{"p":{"a":0,"k":[58,5]}},"ip":0,"op":412,"st":0}]},{"id":"125","layers":[{"ind":123,"ty":0,"parent":117,"ks":{"a":{"a":0,"k":[58,5]}},"w":173,"h":15,"ip":0,"op":412,"st":0,"refId":"121"},{"ind":124,"ty":4,"parent":117,"ks":{"o":{"a":1,"k":[{"t":0,"s":[0],"h":1},{"t":78.78,"s":[0],"h":1},{"t":78.78,"s":[100],"h":1},{"t":411,"s":[100],"h":1}]}},"ip":0,"op":412,"st":0,"shapes":[{"ty":"rc","p":{"a":0,"k":[63.25,5.5]},"r":{"a":0,"k":0},"s":{"a":0,"k":[150.5,13]}},{"ty":"fl","c":{"a":0,"k":[0,0,0]},"o":{"a":0,"k":100}}]},{"ind":117,"ty":3,"ks":{"p":{"a":0,"k":[58,5]}},"ip":0,"op":412,"st":0}]},{"id":"114","layers":[{"ind":113,"ty":4,"parent":112,"ks":{},"ip":0,"op":412,"st":0,"shapes":[{"ty":"rc","p":{"a":0,"k":[57.5,5]},"r":{"a":0,"k":0},"s":{"a":0,"k":[115,10]}},{"ty":"fl","c":{"a":0,"k":[1,1,1]},"o":{"a":0,"k":100}}]},{"ind":112,"ty":3,"parent":111,"ks":{"a":{"a":0,"k":[57.5,5]},"p":{"a":0,"k":[57.5,5]},"s":{"a":1,"k":[{"t":0,"s":[120,120],"i":{"x":[1,1],"y":[1,1]},"o":{"x":[0,0],"y":[0,0]}},{"t":62.82,"s":[120,120],"i":{"x":[0.966,0.966],"y":[0.957,0.957]},"o":{"x":[0.558,0.558],"y":[0,0]}},{"t":73.35,"s":[100,100],"i":{"x":[0.732,0.732],"y":[0.999,0.999]},"o":{"x":[0.394,0.394],"y":[0.787,0.787]}},{"t":75.522,"s":[100.85,100.85],"i":{"x":[0.943,0.943],"y":[0.91,0.91]},"o":{"x":[0.547,0.547],"y":[0.001,0.001]}},{"t":77.688,"s":[100,100],"i":{"x":[1,1],"y":[1,1]},"o":{"x":[0,0],"y":[0,0]}},{"t":78.138,"s":[100.04,100.04],"i":{"x":[1,1],"y":[1,1]},"o":{"x":[0,0],"y":[0,0]}},{"t":78.588,"s":[100,100],"i":{"x":[1,1],"y":[1,1]},"o":{"x":[0,0],"y":[0,0]}},{"t":411,"s":[100,100],"h":1}]}},"ip":0,"op":412,"st":0},{"ind":111,"ty":3,"ks":{"p":{"a":0,"k":[12,1]}},"ip":0,"op":412,"st":0}]},{"id":"128","layers":[{"ind":127,"ty":0,"td":1,"parent":110,"ks":{"a":{"a":0,"k":[58,5]}},"w":231,"h":20,"ip":0,"op":412,"st":0,"refId":"125"},{"ind":116,"ty":0,"tt":1,"parent":110,"ks":{"a":{"a":0,"k":[12,1]}},"w":139,"h":12,"ip":0,"op":412,"st":0,"refId":"114"},{"ind":110,"ty":3,"ks":{"p":{"a":0,"k":[12,1]}},"ip":0,"op":412,"st":0}]},{"id":"142","layers":[{"ind":141,"ty":4,"parent":140,"ks":{},"ip":0,"op":412,"st":0,"shapes":[{"ty":"rc","p":{"a":1,"k":[{"t":0,"s":[0,0],"i":{"x":[1,1],"y":[1,1]},"o":{"x":[0,0],"y":[0,0]}},{"t":39.36,"s":[0,0],"i":{"x":[0.966,0.966],"y":[0.957,0.957]},"o":{"x":[0.558,0.558],"y":[0,0]}},{"t":57.648,"s":[57.5,5],"i":{"x":[0.732,0.732],"y":[0.999,0.999]},"o":{"x":[0.394,0.394],"y":[0.787,0.787]}},{"t":61.416,"s":[55.056,4.787],"i":{"x":[0.943,0.943],"y":[0.91,0.91]},"o":{"x":[0.547,0.547],"y":[0.001,0.001]}},{"t":65.184,"s":[57.499,5],"i":{"x":[1,1],"y":[1,1]},"o":{"x":[0,0],"y":[0,0]}},{"t":65.964,"s":[57.395,4.991],"i":{"x":[1,1],"y":[1,1]},"o":{"x":[0,0],"y":[0,0]}},{"t":66.75,"s":[57.5,5],"i":{"x":[1,1],"y":[1,1]},"o":{"x":[0,0],"y":[0,0]}},{"t":411,"s":[57.5,5],"h":1}]},"r":{"a":0,"k":0},"s":{"a":1,"k":[{"t":0,"s":[0,0],"i":{"x":[1,1],"y":[1,1]},"o":{"x":[0,0],"y":[0,0]}},{"t":39.36,"s":[0,0],"i":{"x":[0.966,0.966],"y":[0.957,0.957]},"o":{"x":[0.558,0.558],"y":[0,0]}},{"t":57.648,"s":[114.999,10],"i":{"x":[0.732,0.732],"y":[0.999,0.999]},"o":{"x":[0.394,0.394],"y":[0.787,0.787]}},{"t":61.416,"s":[110.111,9.575],"i":{"x":[0.943,0.943],"y":[0.91,0.91]},"o":{"x":[0.547,0.547],"y":[0.001,0.001]}},{"t":65.184,"s":[114.998,10],"i":{"x":[1,1],"y":[1,1]},"o":{"x":[0,0],"y":[0,0]}},{"t":65.964,"s":[114.789,9.982],"i":{"x":[1,1],"y":[1,1]},"o":{"x":[0,0],"y":[0,0]}},{"t":66.75,"s":[114.999,10],"i":{"x":[1,1],"y":[1,1]},"o":{"x":[0,0],"y":[0,0]}},{"t":67.08,"s":[115,10],"i":{"x":[1,1],"y":[1,1]},"o":{"x":[0,0],"y":[0,0]}},{"t":411,"s":[115,10],"h":1}]}},{"ty":"fl","c":{"a":0,"k":[0,0,0]},"o":{"a":0,"k":100}}]},{"ind":140,"ty":3,"parent":139,"ks":{},"ip":0,"op":412,"st":0},{"ind":139,"ty":3,"ks":{"p":{"a":0,"k":[58,5]}},"ip":0,"op":412,"st":0}]},{"id":"146","layers":[{"ind":144,"ty":0,"parent":138,"ks":{"a":{"a":0,"k":[58,5]}},"w":173,"h":15,"ip":0,"op":412,"st":0,"refId":"142"},{"ind":145,"ty":4,"parent":138,"ks":{"o":{"a":1,"k":[{"t":0,"s":[0],"h":1},{"t":67.08,"s":[0],"h":1},{"t":67.08,"s":[100],"h":1},{"t":411,"s":[100],"h":1}]}},"ip":0,"op":412,"st":0,"shapes":[{"ty":"rc","p":{"a":0,"k":[63.25,5.5]},"r":{"a":0,"k":0},"s":{"a":0,"k":[150.5,13]}},{"ty":"fl","c":{"a":0,"k":[0,0,0]},"o":{"a":0,"k":100}}]},{"ind":138,"ty":3,"ks":{"p":{"a":0,"k":[58,5]}},"ip":0,"op":412,"st":0}]},{"id":"135","layers":[{"ind":134,"ty":4,"parent":133,"ks":{},"ip":0,"op":412,"st":0,"shapes":[{"ty":"rc","p":{"a":0,"k":[57.5,5]},"r":{"a":0,"k":0},"s":{"a":0,"k":[115,10]}},{"ty":"fl","c":{"a":0,"k":[1,1,1]},"o":{"a":0,"k":100}}]},{"ind":133,"ty":3,"parent":132,"ks":{"a":{"a":0,"k":[57.5,5]},"p":{"a":0,"k":[57.5,5]},"s":{"a":1,"k":[{"t":0,"s":[120,120],"i":{"x":[1,1],"y":[1,1]},"o":{"x":[0,0],"y":[0,0]}},{"t":39.36,"s":[120,120],"i":{"x":[0.966,0.966],"y":[0.957,0.957]},"o":{"x":[0.558,0.558],"y":[0,0]}},{"t":57.648,"s":[100,100],"i":{"x":[0.732,0.732],"y":[0.999,0.999]},"o":{"x":[0.394,0.394],"y":[0.787,0.787]}},{"t":61.416,"s":[100.85,100.85],"i":{"x":[0.943,0.943],"y":[0.91,0.91]},"o":{"x":[0.547,0.547],"y":[0.001,0.001]}},{"t":65.184,"s":[100,100],"i":{"x":[1,1],"y":[1,1]},"o":{"x":[0,0],"y":[0,0]}},{"t":65.964,"s":[100.04,100.04],"i":{"x":[1,1],"y":[1,1]},"o":{"x":[0,0],"y":[0,0]}},{"t":66.75,"s":[100,100],"i":{"x":[1,1],"y":[1,1]},"o":{"x":[0,0],"y":[0,0]}},{"t":411,"s":[100,100],"h":1}]}},"ip":0,"op":412,"st":0},{"ind":132,"ty":3,"ks":{"p":{"a":0,"k":[12,1]}},"ip":0,"op":412,"st":0}]},{"id":"149","layers":[{"ind":148,"ty":0,"td":1,"parent":131,"ks":{"a":{"a":0,"k":[58,5]}},"w":231,"h":20,"ip":0,"op":412,"st":0,"refId":"146"},{"ind":137,"ty":0,"tt":1,"parent":131,"ks":{"a":{"a":0,"k":[12,1]}},"w":139,"h":12,"ip":0,"op":412,"st":0,"refId":"135"},{"ind":131,"ty":3,"ks":{"p":{"a":0,"k":[12,1]}},"ip":0,"op":412,"st":0}]},{"id":"163","layers":[{"ind":162,"ty":4,"parent":161,"ks":{},"ip":0,"op":412,"st":0,"shapes":[{"ty":"rc","p":{"a":1,"k":[{"t":0,"s":[5,0],"i":{"x":[1,0.714],"y":[1,0.428]},"o":{"x":[0,0.378],"y":[0,0.001]}},{"t":24.054,"s":[5,5],"i":{"x":[1,0.624],"y":[1,0.999]},"o":{"x":[0,0.29],"y":[0,0.579]}},{"t":40.896,"s":[5,2.548],"i":{"x":[1,0.764],"y":[1,0.529]},"o":{"x":[0,0.419],"y":[0,0.001]}},{"t":57.738,"s":[5,4.999],"i":{"x":[1,0.688],"y":[1,0.999]},"o":{"x":[0,0.356],"y":[0,0.712]}},{"t":69.534,"s":[5,3.796],"i":{"x":[1,0.654],"y":[1,0.309]},"o":{"x":[0,0.323],"y":[0,0.001]}},{"t":81.324,"s":[5,4.999],"i":{"x":[1,0.583],"y":[1,0.998]},"o":{"x":[0,0.237],"y":[0,0.474]}},{"t":89.598,"s":[5,4.409],"i":{"x":[1,0.758],"y":[1,0.516]},"o":{"x":[0,0.415],"y":[0,0.002]}},{"t":97.872,"s":[5,5],"i":{"x":[1,0.754],"y":[1,0.999]},"o":{"x":[0,0.415],"y":[0,0.828]}},{"t":103.674,"s":[5,4.71],"i":{"x":[1,0.661],"y":[1,0.325]},"o":{"x":[0,0.333],"y":[0,0.003]}},{"t":109.458,"s":[5,5],"i":{"x":[1,0.579],"y":[1,0.996]},"o":{"x":[0,0.232],"y":[0,0.464]}},{"t":113.526,"s":[5,4.857],"i":{"x":[1,0.569],"y":[1,0.142]},"o":{"x":[0,0.227],"y":[0,0.002]}},{"t":117.594,"s":[5,5],"i":{"x":[1,0.596],"y":[1,0.993]},"o":{"x":[0,0.26],"y":[0,0.517]}},{"t":120.45,"s":[5,4.93],"i":{"x":[1,0.921],"y":[1,0.841]},"o":{"x":[0,0.515],"y":[0,0.006]}},{"t":123.312,"s":[5,5],"i":{"x":[1,0.652],"y":[1,0.995]},"o":{"x":[0,0.336],"y":[0,0.666]}},{"t":125.322,"s":[5,4.965],"i":{"x":[1,0.95],"y":[1,0.9]},"o":{"x":[0,0.531],"y":[0,0.014]}},{"t":127.326,"s":[5,5],"i":{"x":[1,0.65],"y":[1,0.99]},"o":{"x":[0,0.342],"y":[0,0.673]}},{"t":128.736,"s":[5,4.983],"i":{"x":[1,0.974],"y":[1,0.948]},"o":{"x":[0,0.545],"y":[0,0.015]}},{"t":130.152,"s":[5,5],"i":{"x":[1,1],"y":[1,1]},"o":{"x":[0,0],"y":[0,0]}},{"t":131.148,"s":[5,4.991],"i":{"x":[1,1],"y":[1,1]},"o":{"x":[0,0],"y":[0,0]}},{"t":132.144,"s":[5,5],"i":{"x":[1,1],"y":[1,1]},"o":{"x":[0,0],"y":[0,0]}},{"t":411,"s":[5,5],"h":1}]},"r":{"a":0,"k":0},"s":{"a":1,"k":[{"t":0,"s":[10,0],"i":{"x":[1,0.714],"y":[1,0.428]},"o":{"x":[0,0.378],"y":[0,0.001]}},{"t":24.054,"s":[10,10],"i":{"x":[1,0.624],"y":[1,0.999]},"o":{"x":[0,0.29],"y":[0,0.579]}},{"t":40.896,"s":[10,5.095],"i":{"x":[1,0.764],"y":[1,0.529]},"o":{"x":[0,0.419],"y":[0,0.001]}},{"t":57.738,"s":[10,9.998],"i":{"x":[1,0.688],"y":[1,0.999]},"o":{"x":[0,0.356],"y":[0,0.712]}},{"t":69.534,"s":[10,7.593],"i":{"x":[1,0.654],"y":[1,0.309]},"o":{"x":[0,0.323],"y":[0,0.001]}},{"t":81.324,"s":[10,9.999],"i":{"x":[1,0.583],"y":[1,0.998]},"o":{"x":[0,0.237],"y":[0,0.474]}},{"t":89.598,"s":[10,8.818],"i":{"x":[1,0.758],"y":[1,0.516]},"o":{"x":[0,0.415],"y":[0,0.002]}},{"t":97.872,"s":[10,10],"i":{"x":[1,0.754],"y":[1,0.999]},"o":{"x":[0,0.415],"y":[0,0.828]}},{"t":103.674,"s":[10,9.419],"i":{"x":[1,0.661],"y":[1,0.325]},"o":{"x":[0,0.333],"y":[0,0.003]}},{"t":109.458,"s":[10,9.999],"i":{"x":[1,0.579],"y":[1,0.996]},"o":{"x":[0,0.232],"y":[0,0.464]}},{"t":113.526,"s":[10,9.714],"i":{"x":[1,0.569],"y":[1,0.142]},"o":{"x":[0,0.227],"y":[0,0.002]}},{"t":117.594,"s":[10,10],"i":{"x":[1,0.596],"y":[1,0.993]},"o":{"x":[0,0.26],"y":[0,0.517]}},{"t":120.45,"s":[10,9.859],"i":{"x":[1,0.921],"y":[1,0.841]},"o":{"x":[0,0.515],"y":[0,0.006]}},{"t":123.312,"s":[10,10],"i":{"x":[1,0.652],"y":[1,0.995]},"o":{"x":[0,0.336],"y":[0,0.666]}},{"t":125.322,"s":[10,9.93],"i":{"x":[1,0.95],"y":[1,0.9]},"o":{"x":[0,0.531],"y":[0,0.014]}},{"t":127.326,"s":[10,10],"i":{"x":[1,0.65],"y":[1,0.99]},"o":{"x":[0,0.342],"y":[0,0.673]}},{"t":128.736,"s":[10,9.965],"i":{"x":[1,0.974],"y":[1,0.948]},"o":{"x":[0,0.545],"y":[0,0.015]}},{"t":130.152,"s":[10,10],"i":{"x":[1,1],"y":[1,1]},"o":{"x":[0,0],"y":[0,0]}},{"t":131.148,"s":[10,9.983],"i":{"x":[1,1],"y":[1,1]},"o":{"x":[0,0],"y":[0,0]}},{"t":132.144,"s":[10,10],"i":{"x":[1,1],"y":[1,1]},"o":{"x":[0,0],"y":[0,0]}},{"t":411,"s":[10,10],"h":1}]}},{"ty":"fl","c":{"a":0,"k":[0,0,0]},"o":{"a":0,"k":100}}]},{"ind":161,"ty":3,"parent":160,"ks":{"p":{"a":1,"k":[{"t":0,"s":[0,10],"i":{"x":[1,0.714],"y":[1,0.428]},"o":{"x":[0,0.378],"y":[0,0.001]}},{"t":24.054,"s":[0,0],"i":{"x":[1,0.624],"y":[1,0.999]},"o":{"x":[0,0.29],"y":[0,0.579]}},{"t":40.896,"s":[0,4.905],"i":{"x":[1,0.764],"y":[1,0.529]},"o":{"x":[0,0.419],"y":[0,0.001]}},{"t":57.738,"s":[0,0.002],"i":{"x":[1,0.688],"y":[1,0.999]},"o":{"x":[0,0.356],"y":[0,0.712]}},{"t":69.534,"s":[0,2.407],"i":{"x":[1,0.654],"y":[1,0.309]},"o":{"x":[0,0.323],"y":[0,0.001]}},{"t":81.324,"s":[0,0.001],"i":{"x":[1,0.583],"y":[1,0.998]},"o":{"x":[0,0.237],"y":[0,0.474]}},{"t":89.598,"s":[0,1.182],"i":{"x":[1,0.758],"y":[1,0.516]},"o":{"x":[0,0.415],"y":[0,0.002]}},{"t":97.872,"s":[0,0],"i":{"x":[1,0.754],"y":[1,0.999]},"o":{"x":[0,0.415],"y":[0,0.828]}},{"t":103.674,"s":[0,0.581],"i":{"x":[1,0.661],"y":[1,0.325]},"o":{"x":[0,0.333],"y":[0,0.003]}},{"t":109.458,"s":[0,0.001],"i":{"x":[1,0.579],"y":[1,0.996]},"o":{"x":[0,0.232],"y":[0,0.464]}},{"t":113.526,"s":[0,0.286],"i":{"x":[1,0.569],"y":[1,0.142]},"o":{"x":[0,0.227],"y":[0,0.002]}},{"t":117.594,"s":[0,0],"i":{"x":[1,0.596],"y":[1,0.993]},"o":{"x":[0,0.26],"y":[0,0.517]}},{"t":120.45,"s":[0,0.141],"i":{"x":[1,0.921],"y":[1,0.841]},"o":{"x":[0,0.515],"y":[0,0.006]}},{"t":123.312,"s":[0,0],"i":{"x":[1,0.652],"y":[1,0.995]},"o":{"x":[0,0.336],"y":[0,0.666]}},{"t":125.322,"s":[0,0.07],"i":{"x":[1,0.95],"y":[1,0.9]},"o":{"x":[0,0.531],"y":[0,0.014]}},{"t":127.326,"s":[0,0],"i":{"x":[1,0.65],"y":[1,0.99]},"o":{"x":[0,0.342],"y":[0,0.673]}},{"t":128.736,"s":[0,0.035],"i":{"x":[1,0.974],"y":[1,0.948]},"o":{"x":[0,0.545],"y":[0,0.015]}},{"t":130.152,"s":[0,0],"i":{"x":[1,1],"y":[1,1]},"o":{"x":[0,0],"y":[0,0]}},{"t":131.148,"s":[0,0.017],"i":{"x":[1,1],"y":[1,1]},"o":{"x":[0,0],"y":[0,0]}},{"t":132.144,"s":[0,0],"i":{"x":[1,1],"y":[1,1]},"o":{"x":[0,0],"y":[0,0]}},{"t":411,"s":[0,0],"h":1}]}},"ip":0,"op":412,"st":0},{"ind":160,"ty":3,"ks":{"p":{"a":0,"k":[0,5]}},"ip":0,"op":412,"st":0}]},{"id":"167","layers":[{"ind":165,"ty":0,"parent":159,"ks":{"a":{"a":0,"k":[0,5]}},"w":10,"h":25,"ip":0,"op":412,"st":0,"refId":"163"},{"ind":166,"ty":4,"parent":159,"ks":{"o":{"a":1,"k":[{"t":0,"s":[0],"h":1},{"t":136.5,"s":[0],"h":1},{"t":136.5,"s":[100],"h":1},{"t":411,"s":[100],"h":1}]}},"ip":0,"op":412,"st":0,"shapes":[{"ty":"rc","p":{"a":0,"k":[5.5,5.5]},"r":{"a":0,"k":0},"s":{"a":0,"k":[13,13]}},{"ty":"fl","c":{"a":0,"k":[0,0,0]},"o":{"a":0,"k":100}}]},{"ind":159,"ty":3,"ks":{"p":{"a":0,"k":[1,5]}},"ip":0,"op":412,"st":0}]},{"id":"156","layers":[{"ind":155,"ty":4,"parent":154,"ks":{},"ip":0,"op":412,"st":0,"shapes":[{"ty":"rc","p":{"a":0,"k":[5,5]},"r":{"a":0,"k":0},"s":{"a":0,"k":[10,10]}},{"ty":"fl","c":{"a":0,"k":[1,1,1]},"o":{"a":0,"k":100}}]},{"ind":154,"ty":3,"parent":153,"ks":{"a":{"a":0,"k":[5,5]},"p":{"a":0,"k":[5,5]},"s":{"a":1,"k":[{"t":0,"s":[120,120],"i":{"x":[0.714,0.714],"y":[0.428,0.428]},"o":{"x":[0.378,0.378],"y":[0.001,0.001]}},{"t":24.054,"s":[100,100],"i":{"x":[0.624,0.624],"y":[0.999,0.999]},"o":{"x":[0.29,0.29],"y":[0.579,0.579]}},{"t":40.896,"s":[109.81,109.81],"i":{"x":[0.764,0.764],"y":[0.529,0.529]},"o":{"x":[0.419,0.419],"y":[0.001,0.001]}},{"t":57.738,"s":[100,100],"i":{"x":[0.688,0.688],"y":[0.999,0.999]},"o":{"x":[0.356,0.356],"y":[0.712,0.712]}},{"t":69.534,"s":[104.81,104.81],"i":{"x":[0.654,0.654],"y":[0.309,0.309]},"o":{"x":[0.323,0.323],"y":[0.001,0.001]}},{"t":81.324,"s":[100,100],"i":{"x":[0.583,0.583],"y":[0.998,0.998]},"o":{"x":[0.237,0.237],"y":[0.474,0.474]}},{"t":89.598,"s":[102.36,102.36],"i":{"x":[0.758,0.758],"y":[0.516,0.516]},"o":{"x":[0.415,0.415],"y":[0.002,0.002]}},{"t":97.872,"s":[100,100],"i":{"x":[0.754,0.754],"y":[0.999,0.999]},"o":{"x":[0.415,0.415],"y":[0.828,0.828]}},{"t":103.674,"s":[101.16,101.16],"i":{"x":[0.661,0.661],"y":[0.325,0.325]},"o":{"x":[0.333,0.333],"y":[0.003,0.003]}},{"t":109.458,"s":[100,100],"i":{"x":[0.579,0.579],"y":[0.996,0.996]},"o":{"x":[0.232,0.232],"y":[0.464,0.464]}},{"t":113.526,"s":[100.57,100.57],"i":{"x":[0.569,0.569],"y":[0.142,0.142]},"o":{"x":[0.227,0.227],"y":[0.002,0.002]}},{"t":117.594,"s":[100,100],"i":{"x":[0.596,0.596],"y":[0.993,0.993]},"o":{"x":[0.26,0.26],"y":[0.517,0.517]}},{"t":120.45,"s":[100.28,100.28],"i":{"x":[0.921,0.921],"y":[0.841,0.841]},"o":{"x":[0.515,0.515],"y":[0.006,0.006]}},{"t":123.312,"s":[100,100],"i":{"x":[0.652,0.652],"y":[0.995,0.995]},"o":{"x":[0.336,0.336],"y":[0.666,0.666]}},{"t":125.322,"s":[100.14,100.14],"i":{"x":[0.95,0.95],"y":[0.9,0.9]},"o":{"x":[0.531,0.531],"y":[0.014,0.014]}},{"t":127.326,"s":[100,100],"i":{"x":[0.65,0.65],"y":[0.99,0.99]},"o":{"x":[0.342,0.342],"y":[0.673,0.673]}},{"t":128.736,"s":[100.07,100.07],"i":{"x":[0.974,0.974],"y":[0.948,0.948]},"o":{"x":[0.545,0.545],"y":[0.015,0.015]}},{"t":130.152,"s":[100,100],"i":{"x":[1,1],"y":[1,1]},"o":{"x":[0,0],"y":[0,0]}},{"t":131.148,"s":[100.03,100.03],"i":{"x":[1,1],"y":[1,1]},"o":{"x":[0,0],"y":[0,0]}},{"t":132.144,"s":[100,100],"i":{"x":[1,1],"y":[1,1]},"o":{"x":[0,0],"y":[0,0]}},{"t":411,"s":[100,100],"h":1}]}},"ip":0,"op":412,"st":0},{"ind":153,"ty":3,"ks":{"p":{"a":0,"k":[1,1]}},"ip":0,"op":412,"st":0}]},{"id":"170","layers":[{"ind":25,"ty":0,"parent":4,"ks":{"a":{"a":0,"k":[4,1]},"o":{"a":1,"k":[{"t":0,"s":[0],"h":1},{"t":46.86,"s":[0],"h":1},{"t":46.86,"s":[100],"h":1},{"t":411,"s":[100],"h":1}]},"p":{"a":0,"k":[20,22]}},"w":52,"h":13,"ip":0,"op":412,"st":0,"refId":"23"},{"ind":46,"ty":0,"parent":4,"ks":{"a":{"a":0,"k":[1,1]},"o":{"a":1,"k":[{"t":0,"s":[0],"h":1},{"t":108.42,"s":[0],"h":1},{"t":108.42,"s":[100],"h":1},{"t":411,"s":[100],"h":1}]},"p":{"a":0,"k":[113,122]}},"w":10,"h":13,"ip":0,"op":412,"st":0,"refId":"44"},{"ind":67,"ty":0,"parent":4,"ks":{"a":{"a":0,"k":[9,1]},"o":{"a":1,"k":[{"t":0,"s":[0],"h":1},{"t":95.82,"s":[0],"h":1},{"t":95.82,"s":[100],"h":1},{"t":411,"s":[100],"h":1}]},"p":{"a":0,"k":[20,122]}},"w":117,"h":13,"ip":0,"op":412,"st":0,"refId":"65"},{"ind":88,"ty":0,"parent":4,"ks":{"a":{"a":0,"k":[12,1]},"o":{"a":1,"k":[{"t":0,"s":[0],"h":1},{"t":84.54,"s":[0],"h":1},{"t":84.54,"s":[100],"h":1},{"t":411,"s":[100],"h":1}]},"p":{"a":0,"k":[20,100]}},"w":151,"h":13,"ip":0,"op":412,"st":0,"refId":"86"},{"ind":109,"ty":0,"parent":4,"ks":{"a":{"a":0,"k":[12,1]},"o":{"a":1,"k":[{"t":0,"s":[0],"h":1},{"t":69.3,"s":[0],"h":1},{"t":69.3,"s":[100],"h":1},{"t":411,"s":[100],"h":1}]},"p":{"a":0,"k":[20,78]}},"w":151,"h":13,"ip":0,"op":412,"st":0,"refId":"107"},{"ind":130,"ty":0,"parent":4,"ks":{"a":{"a":0,"k":[12,1]},"o":{"a":1,"k":[{"t":0,"s":[0],"h":1},{"t":62.82,"s":[0],"h":1},{"t":62.82,"s":[100],"h":1},{"t":411,"s":[100],"h":1}]},"p":{"a":0,"k":[20,56]}},"w":151,"h":13,"ip":0,"op":412,"st":0,"refId":"128"},{"ind":151,"ty":0,"parent":4,"ks":{"a":{"a":0,"k":[12,1]},"o":{"a":1,"k":[{"t":0,"s":[0],"h":1},{"t":39.36,"s":[0],"h":1},{"t":39.36,"s":[100],"h":1},{"t":411,"s":[100],"h":1}]},"p":{"a":0,"k":[20,0]}},"w":151,"h":13,"ip":0,"op":412,"st":0,"refId":"149"},{"ind":169,"ty":0,"td":1,"parent":152,"ks":{"a":{"a":0,"k":[1,5]}},"w":13,"h":30,"ip":0,"op":412,"st":0,"refId":"167"},{"ind":158,"ty":0,"tt":1,"parent":152,"ks":{"a":{"a":0,"k":[1,1]}},"w":12,"h":12,"ip":0,"op":412,"st":0,"refId":"156"},{"ind":152,"ty":3,"parent":4,"ks":{},"ip":0,"op":412,"st":0},{"ind":4,"ty":3,"parent":3,"ks":{"a":{"a":0,"k":[67.5,66]},"p":{"a":0,"k":[67.5,66]},"s":{"a":1,"k":[{"t":0,"s":[100,100],"i":{"x":[1,1],"y":[1,1]},"o":{"x":[0,0],"y":[0,0]}},{"t":151.62,"s":[100,100],"i":{"x":[0.2,0.2],"y":[1,1]},"o":{"x":[0.8,0.8],"y":[0,0]}},{"t":194.76,"s":[120,120],"i":{"x":[1,1],"y":[1,1]},"o":{"x":[0,0],"y":[0,0]}},{"t":411,"s":[120,120],"h":1}]}},"ip":0,"op":412,"st":0},{"ind":3,"ty":3,"ks":{"p":{"a":0,"k":[15,15]}},"ip":0,"op":412,"st":0}]},{"id":"197","layers":[{"ind":196,"ty":4,"parent":195,"ks":{},"ip":0,"op":412,"st":0,"shapes":[{"ty":"rc","p":{"a":1,"k":[{"t":0,"s":[0,0],"i":{"x":[1,1],"y":[1,1]},"o":{"x":[0,0],"y":[0,0]}},{"t":175.86,"s":[0,0],"i":{"x":[0,0],"y":[1,1]},"o":{"x":[0.5,0.5],"y":[0,0]}},{"t":219,"s":[60.5,60.5],"i":{"x":[1,1],"y":[1,1]},"o":{"x":[0,0],"y":[0,0]}},{"t":411,"s":[60.5,60.5],"h":1}]},"r":{"a":0,"k":0},"s":{"a":1,"k":[{"t":0,"s":[0,0],"i":{"x":[1,1],"y":[1,1]},"o":{"x":[0,0],"y":[0,0]}},{"t":175.86,"s":[0,0],"i":{"x":[0,0],"y":[1,1]},"o":{"x":[0.5,0.5],"y":[0,0]}},{"t":219,"s":[121,121],"i":{"x":[1,1],"y":[1,1]},"o":{"x":[0,0],"y":[0,0]}},{"t":411,"s":[121,121],"h":1}]}},{"ty":"fl","c":{"a":0,"k":[0,0,0]},"o":{"a":0,"k":100}}]},{"ind":195,"ty":3,"parent":194,"ks":{"p":{"a":1,"k":[{"t":0,"s":[60.5,60.5],"i":{"x":[1,1],"y":[1,1]},"o":{"x":[0,0],"y":[0,0]}},{"t":175.86,"s":[60.5,60.5],"i":{"x":[0,0],"y":[1,1]},"o":{"x":[0.5,0.5],"y":[0,0]}},{"t":219,"s":[0,0],"i":{"x":[1,1],"y":[1,1]},"o":{"x":[0,0],"y":[0,0]}},{"t":411,"s":[0,0],"h":1}]}},"ip":0,"op":412,"st":0},{"ind":194,"ty":3,"ks":{"p":{"a":0,"k":[61,61]}},"ip":0,"op":412,"st":0}]},{"id":"201","layers":[{"ind":199,"ty":0,"parent":193,"ks":{"a":{"a":0,"k":[61,61]}},"w":243,"h":243,"ip":0,"op":412,"st":0,"refId":"197"},{"ind":200,"ty":4,"parent":193,"ks":{"o":{"a":1,"k":[{"t":0,"s":[0],"h":1},{"t":219,"s":[0],"h":1},{"t":219,"s":[100],"h":1},{"t":411,"s":[100],"h":1}]}},"ip":0,"op":412,"st":0,"shapes":[{"ty":"rc","p":{"a":0,"k":[326.126,328.448]},"r":{"a":0,"k":0},"s":{"a":0,"k":[676.452,681.096]}},{"ty":"fl","c":{"a":0,"k":[0,0,0]},"o":{"a":0,"k":100}}]},{"ind":193,"ty":3,"ks":{"p":{"a":0,"k":[61,61]}},"ip":0,"op":412,"st":0}]},{"id":"187","layers":[{"ind":186,"ty":4,"ks":{},"ip":0,"op":412,"st":0,"shapes":[{"ty":"rc","p":{"a":0,"k":[281.855,283.79]},"r":{"a":0,"k":0},"s":{"a":0,"k":[563.71,567.58]}},{"ty":"fl","c":{"a":0,"k":[0,0,0,0]},"o":{"a":0,"k":0}}]},{"ind":0,"ty":4,"ks":{"s":{"a":0,"k":[133.4,133.43]}},"ip":0,"op":412,"st":0,"shapes":[{"ty":"gr","it":[{"ty":"gr","it":[{"ty":"gr","it":[{"ty":"sh","ks":{"a":0,"k":{"c":true,"i":[[0,0],[9.87,5.2],[5.97,31.16],[0,0],[0.3,5.92],[0,0],[0,0],[0,0],[0,0],[0,0],[2.41,0.38]],"o":[[-11.42,-1.3],[-28.04,-14.25],[0,0],[-1.09,-5.83],[0,0],[0,0],[0,0],[0,0],[0,0],[-2.4,0.39],[0,0]],"v":[[301.51,425.39],[268.79,413.96],[213.47,343.84],[213.47,343.84],[211.39,326.18],[210.88,214.77],[421.49,213.47],[422.79,424.87],[352.39,425.09],[308.77,425.36],[301.51,425.39]]}}},{"ty":"fl","c":{"a":0,"k":[1,1,1,1]},"o":{"a":0,"k":100}},{"ty":"tr","o":{"a":0,"k":100}}]},{"ty":"tr","o":{"a":0,"k":100}}]},{"ty":"gr","it":[{"ty":"sh","ks":{"a":0,"k":{"c":true,"i":[[0,0],[-9.87,-5.2],[-5.98,-31.16],[0,0],[-0.09,-5.93],[0,0],[0,0],[0,0],[0,0],[-2.41,-0.22]],"o":[[11.17,1.3],[27.75,14.54],[0,0],[1.14,5.82],[0,0],[0,0],[0,0],[0,0],[2.43,-0.05],[0,0]],"v":[[121.02,0.26],[153.74,11.95],[208.8,82.32],[208.8,82.33],[210.64,99.98],[210.64,211.39],[0,211.39],[0,0],[113.75,0],[121.02,0.26]]}}},{"ty":"fl","c":{"a":0,"k":[1,1,1,1]},"o":{"a":0,"k":100}},{"ty":"tr","o":{"a":0,"k":100}}]},{"ty":"gr","it":[{"ty":"sh","ks":{"a":0,"k":{"c":true,"i":[[0,0],[9.17,-11.17],[15.79,-8.18],[14.68,0.01],[15.32,6.75],[10.16,14.58],[0,17.92],[0,0],[0,0],[0,0],[0,-16.34],[0,0],[1.89,-7.47]],"o":[[-3.68,13.98],[-10.68,14.22],[-13.16,6.5],[-16.09,0],[-16.18,-7.35],[-10.39,-14.25],[0,0],[0,0],[0,0],[0,16.36],[0,0],[0.17,7.7],[0,0]],"v":[[418.11,136.34],[398.61,174.52],[358.39,208.54],[316.07,218.41],[269.84,210.61],[229.59,177.11],[209.34,127.25],[209.34,7.01],[419.95,7.01],[419.95,64.15],[420.7,113.49],[420.7,113.49],[418.11,136.34]]}}},{"ty":"fl","c":{"a":0,"k":[1,1,1,1]},"o":{"a":0,"k":100}},{"ty":"tr","o":{"a":0,"k":100}}]},{"ty":"gr","it":[{"ty":"sh","ks":{"a":0,"k":{"c":true,"i":[[0,0],[-9.17,11.18],[-15.8,8.17],[-14.68,-0.01],[-15.32,-6.75],[-10.17,-14.58],[0,-17.92],[0,0],[0,0],[0,0],[0,16.34],[-1.79,7.53]],"o":[[3.68,-13.98],[10.69,-14.22],[13.16,-6.5],[16.1,0],[16.19,7.35],[10.39,14.25],[0,0],[0,0],[0,0],[0,-16.36],[-0.59,-7.53],[0,0]],"v":[[4.39,289.82],[23.89,251.65],[64.15,217.63],[106.48,207.76],[152.7,215.55],[192.96,249.05],[213.21,298.91],[213.21,419.15],[2.89,419.15],[2.89,362.02],[2.14,312.67],[4.39,289.82]]}}},{"ty":"fl","c":{"a":0,"k":[1,1,1,1]},"o":{"a":0,"k":100}},{"ty":"tr","o":{"a":0,"k":100}}]},{"ty":"tr","o":{"a":0,"k":100}}]}]}]},{"id":"190","layers":[{"ind":189,"ty":0,"parent":185,"ks":{"s":{"a":0,"k":[99.95,99.93]}},"w":564,"h":568,"ip":0,"op":412,"st":0,"refId":"187"},{"ind":185,"ty":3,"ks":{"s":{"a":0,"k":[21.46,21.32]}},"ip":0,"op":412,"st":0}]},{"id":"209","layers":[{"ind":208,"ty":4,"parent":207,"ks":{},"ip":0,"op":412,"st":0,"shapes":[{"ty":"sh","ks":{"a":0,"k":{"c":true,"i":[[0,0],[0,0],[3.1,1.6],[1.8,3],[0,4.3],[0,0],[0,0],[-1.8,3],[-3.1,1.6],[-3.9,0],[0,0],[-3.1,-1.6],[-1.8,-3],[0,-4.3],[0,0],[0,0],[1.8,-3],[3.1,-1.6],[3.9,0]],"v":[[24.5,76.8],[24.5,76.8],[13.8,74.4],[6.4,67.4],[3.7,56.5],[3.7,56.5],[3.7,55.2],[6.4,44.2],[13.8,37.3],[24.5,34.9],[24.5,34.9],[35.1,37.3],[42.6,44.2],[45.3,55.2],[45.3,55.2],[45.3,56.5],[42.6,67.4],[35.1,74.4],[24.5,76.8]],"o":[[0,0],[-3.9,0],[-3.1,-1.6],[-1.8,-3],[0,0],[0,0],[0,-4.3],[1.8,-3],[3.1,-1.6],[0,0],[3.9,0],[3.1,1.6],[1.8,3],[0,0],[0,0],[0,4.3],[-1.8,3],[-3.1,1.6],[0,0]]}}},{"ty":"sh","ks":{"a":0,"k":{"c":true,"i":[[0,0],[0,0],[-2,2],[0,3.7],[0,0],[0,0],[2,2],[3.1,0],[0,0],[2,-2],[0,-3.7],[0,0],[0,0],[-2,-2],[-3.1,0]],"v":[[24.5,67.8],[24.5,67.8],[32.2,64.8],[35.2,56.2],[35.2,56.2],[35.2,55.4],[32.2,46.8],[24.5,43.8],[24.5,43.8],[16.8,46.8],[13.8,55.4],[13.8,55.4],[13.8,56.2],[16.8,64.8],[24.5,67.8]],"o":[[0,0],[3.1,0],[2,-2],[0,0],[0,0],[0,-3.7],[-2,-2],[0,0],[-3.1,0],[-2,2],[0,0],[0,0],[0,3.7],[2,2],[0,0]]}}},{"ty":"fl","c":{"a":0,"k":[1,1,1]},"o":{"a":0,"k":100}}]},{"ind":207,"ty":3,"ks":{"p":{"a":0,"k":[-3,-34]}},"ip":0,"op":412,"st":0}]},{"id":"214","layers":[{"ind":213,"ty":4,"parent":212,"ks":{},"ip":0,"op":412,"st":0,"shapes":[{"ty":"sh","ks":{"a":0,"k":{"c":true,"i":[[0,0],[0,0],[0,0],[0,0],[0,0]],"v":[[15.7,75.7],[5.6,75.7],[5.6,36],[15.7,36],[15.7,75.7]],"o":[[0,0],[0,0],[0,0],[0,0],[0,0]]}}},{"ty":"sh","ks":{"a":0,"k":{"c":true,"i":[[0,0],[0,0],[1.3,1.2],[0,1.9],[0,0],[-1.3,1.2],[-1.8,0],[0,0],[-1.2,-1.2],[0,-1.9],[0,0],[1.2,-1.2],[1.9,0]],"v":[[10.6,31.4],[10.6,31.4],[6,29.6],[4.2,25],[4.2,25],[6,20.3],[10.6,18.6],[10.6,18.6],[15.3,20.3],[17.1,25],[17.1,25],[15.3,29.6],[10.6,31.4]],"o":[[0,0],[-1.8,0],[-1.3,-1.2],[0,0],[0,-1.9],[1.3,-1.2],[0,0],[1.9,0],[1.2,1.2],[0,0],[0,1.9],[-1.2,1.2],[0,0]]}}},{"ty":"fl","c":{"a":0,"k":[1,1,1]},"o":{"a":0,"k":100}}]},{"ind":212,"ty":3,"ks":{"p":{"a":0,"k":[-4,-18]}},"ip":0,"op":412,"st":0}]},{"id":"219","layers":[{"ind":218,"ty":4,"parent":217,"ks":{},"ip":0,"op":412,"st":0,"shapes":[{"ty":"sh","ks":{"a":0,"k":{"c":true,"i":[[0,0],[0,0],[1.5,1.4],[0,2.2],[0,0],[-1.5,1.4],[-2.2,0],[0,0],[-1.4,-1.4],[0,-2.2],[0,0],[1.4,-1.4],[2.1,0]],"v":[[12,76.8],[12,76.8],[6.5,74.7],[4.3,69.2],[4.3,69.2],[6.5,63.7],[12,61.6],[12,61.6],[17.4,63.7],[19.5,69.2],[19.5,69.2],[17.4,74.7],[12,76.8]],"o":[[0,0],[-2.2,0],[-1.5,-1.4],[0,0],[0,-2.2],[1.5,-1.4],[0,0],[2.1,0],[1.4,1.4],[0,0],[0,2.2],[-1.4,1.4],[0,0]]}}},{"ty":"fl","c":{"a":0,"k":[1,1,1]},"o":{"a":0,"k":100}}]},{"ind":217,"ty":3,"ks":{"p":{"a":0,"k":[-4,-61]}},"ip":0,"op":412,"st":0}]},{"id":"224","layers":[{"ind":223,"ty":4,"parent":222,"ks":{},"ip":0,"op":412,"st":0,"shapes":[{"ty":"sh","ks":{"a":0,"k":{"c":true,"i":[[0,0],[0,0],[0,0],[0,0],[0,1.6],[0,0],[0,0],[0,0],[0.9,-0.9],[1.5,-0.6],[2.4,0],[0,0],[2.3,1.4],[1.3,2.5],[0,3.3],[0,0],[0,0],[0,0],[0,0],[-1.5,-1.5],[-2.7,0],[0,0],[-1.7,2.1],[0,3.7],[0,0],[0,0],[0,0],[0,0],[1.6,-1.6],[2.7,0],[0,0]],"v":[[34.9,91.7],[9.9,91.7],[9.9,82.9],[31.5,82.9],[33.8,80.5],[33.8,80.5],[33.8,70.5],[32.3,70.5],[30.3,73.2],[26.6,75.4],[20.7,76.3],[20.7,76.3],[12.6,74.2],[7.2,68.3],[5.3,59.7],[5.3,59.7],[5.3,36],[15.4,36],[15.4,58.9],[17.6,65.6],[23.8,67.8],[23.8,67.8],[31,64.8],[33.6,56.2],[33.6,56.2],[33.6,36],[43.7,36],[43.7,82.7],[41.3,89.2],[34.9,91.7],[34.9,91.7]],"o":[[0,0],[0,0],[0,0],[1.5,0],[0,0],[0,0],[0,0],[-0.4,0.9],[-0.9,0.9],[-1.5,0.6],[0,0],[-3.1,0],[-2.3,-1.4],[-1.3,-2.5],[0,0],[0,0],[0,0],[0,0],[0,3],[1.5,1.5],[0,0],[3.1,0],[1.7,-2.1],[0,0],[0,0],[0,0],[0,0],[0,2.7],[-1.6,1.6],[0,0],[0,0]]}}},{"ty":"fl","c":{"a":0,"k":[1,1,1]},"o":{"a":0,"k":100}}]},{"ind":222,"ty":3,"ks":{"p":{"a":0,"k":[-5,-36]}},"ip":0,"op":412,"st":0}]},{"id":"229","layers":[{"ind":228,"ty":4,"parent":227,"ks":{},"ip":0,"op":412,"st":0,"shapes":[{"ty":"sh","ks":{"a":0,"k":{"c":true,"i":[[0,0],[0,0],[1.6,1.6],[0,2.7],[0,0],[0,0],[0,0],[0,0],[0,0],[0,0],[0,0],[0,0],[0,0],[0,0],[0,0],[0,0],[-1.5,0],[0,0],[0,0],[0,0]],"v":[[32,75.7],[20.8,75.7],[14.4,73.2],[12,66.7],[12,66.7],[12,44.3],[2.1,44.3],[2.1,36],[12,36],[12,23.7],[22.1,23.7],[22.1,36],[33,36],[33,44.3],[22.1,44.3],[22.1,65],[24.3,67.4],[24.3,67.4],[32,67.4],[32,75.7]],"o":[[0,0],[-2.6,0],[-1.6,-1.6],[0,0],[0,0],[0,0],[0,0],[0,0],[0,0],[0,0],[0,0],[0,0],[0,0],[0,0],[0,0],[0,1.6],[0,0],[0,0],[0,0],[0,0]]}}},{"ty":"fl","c":{"a":0,"k":[1,1,1]},"o":{"a":0,"k":100}}]},{"ind":227,"ty":3,"ks":{"p":{"a":0,"k":[-2,-23]}},"ip":0,"op":412,"st":0}]},{"id":"234","layers":[{"ind":233,"ty":4,"parent":232,"ks":{},"ip":0,"op":412,"st":0,"shapes":[{"ty":"sh","ks":{"a":0,"k":{"c":true,"i":[[0,0],[0,0],[0,0],[0,0],[0,0]],"v":[[15.7,75.7],[5.6,75.7],[5.6,36],[15.7,36],[15.7,75.7]],"o":[[0,0],[0,0],[0,0],[0,0],[0,0]]}}},{"ty":"sh","ks":{"a":0,"k":{"c":true,"i":[[0,0],[0,0],[1.3,1.2],[0,1.9],[0,0],[-1.3,1.2],[-1.8,0],[0,0],[-1.2,-1.2],[0,-1.9],[0,0],[1.2,-1.2],[1.9,0]],"v":[[10.6,31.4],[10.6,31.4],[6,29.6],[4.2,25],[4.2,25],[6,20.3],[10.6,18.6],[10.6,18.6],[15.3,20.3],[17.1,25],[17.1,25],[15.3,29.6],[10.6,31.4]],"o":[[0,0],[-1.8,0],[-1.3,-1.2],[0,0],[0,-1.9],[1.3,-1.2],[0,0],[1.9,0],[1.2,1.2],[0,0],[0,1.9],[-1.2,1.2],[0,0]]}}},{"ty":"fl","c":{"a":0,"k":[1,1,1]},"o":{"a":0,"k":100}}]},{"ind":232,"ty":3,"ks":{"p":{"a":0,"k":[-4,-18]}},"ip":0,"op":412,"st":0}]},{"id":"239","layers":[{"ind":238,"ty":4,"parent":237,"ks":{},"ip":0,"op":412,"st":0,"shapes":[{"ty":"sh","ks":{"a":0,"k":{"c":true,"i":[[0,0],[0,0],[0,0],[0,0],[0,0],[0,0],[-1.4,0.7],[-1.8,0],[0,0],[0,0],[0,0],[0,0],[1.7,-1.4],[0,-2.8],[0,0],[0,0]],"v":[[15.7,75.7],[5.6,75.7],[5.6,36],[15.5,36],[15.5,40.5],[17,40.5],[19.9,37],[24.6,35.8],[24.6,35.8],[29.4,35.8],[29.4,44.8],[24.5,44.8],[18.2,46.8],[15.7,53.1],[15.7,53.1],[15.7,75.7]],"o":[[0,0],[0,0],[0,0],[0,0],[0,0],[0.6,-1.6],[1.4,-0.7],[0,0],[0,0],[0,0],[0,0],[-2.6,0],[-1.7,1.4],[0,0],[0,0],[0,0]]}}},{"ty":"fl","c":{"a":0,"k":[1,1,1]},"o":{"a":0,"k":100}}]},{"ind":237,"ty":3,"ks":{"p":{"a":0,"k":[-5,-35]}},"ip":0,"op":412,"st":0}]},{"id":"244","layers":[{"ind":243,"ty":4,"parent":242,"ks":{},"ip":0,"op":412,"st":0,"shapes":[{"ty":"sh","ks":{"a":0,"k":{"c":true,"i":[[0,0],[0,0],[2.2,1],[1.3,1.9],[0,2.7],[0,0],[-1.3,1.8],[-2.3,0.9],[-3,0],[0,0],[0,0],[0,0],[1.2,1.2],[2.6,0],[0,0],[1.2,-1.1],[0.4,-1.8],[0,0],[0,0],[-1.4,1.7],[-2.4,1],[-3.4,0],[0,0],[-3,-2.6],[0,-5],[0,0],[0,0],[-1.5,0],[0,0],[0,0],[0,0],[0,0],[1.3,1],[0,1.6],[0,0],[0,0],[0,0],[0.7,-1],[1.6,-0.8],[2.8,0]],"v":[[17.9,76.8],[17.9,76.8],[10.3,75.3],[5,71],[3,64.1],[3,64.1],[5,57.2],[10.4,53.1],[18.4,51.7],[18.4,51.7],[29.3,51.7],[29.3,49.4],[27.5,44.8],[21.9,43],[21.9,43],[16.3,44.8],[13.9,49.2],[13.9,49.2],[4.6,46.1],[7.7,40.5],[13.4,36.4],[22.1,34.9],[22.1,34.9],[34.5,38.8],[39,50.2],[39,50.2],[39,65],[41.3,67.4],[41.3,67.4],[44.5,67.4],[44.5,75.7],[37.8,75.7],[32.9,74.2],[31,70.4],[31,70.4],[31,70.3],[29.4,70.3],[28,72.8],[24.5,75.6],[17.9,76.8]],"o":[[0,0],[-2.8,0],[-2.2,-1],[-1.3,-1.9],[0,0],[0,-2.7],[1.3,-1.8],[2.3,-0.9],[0,0],[0,0],[0,0],[0,-1.9],[-1.2,-1.2],[0,0],[-2.5,0],[-1.2,1.1],[0,0],[0,0],[0.6,-2],[1.4,-1.7],[2.4,-1],[0,0],[5.2,0],[3,2.6],[0,0],[0,0],[0,1.6],[0,0],[0,0],[0,0],[0,0],[-2,0],[-1.3,-1],[0,0],[0,0],[0,0],[-0.2,0.6],[-0.7,1],[-1.6,0.8],[0,0]]}}},{"ty":"sh","ks":{"a":0,"k":{"c":true,"i":[[0,0],[0,0],[-1.8,1.6],[0,2.6],[0,0],[0,0],[0,0],[1.1,-0.8],[0,-1.4],[0,0],[-1.1,-0.9],[-2.1,0]],"v":[[19.7,68.6],[19.7,68.6],[26.6,66.3],[29.3,60],[29.3,60],[29.3,59.2],[19.1,59.2],[14.7,60.4],[13.1,63.8],[13.1,63.8],[14.8,67.3],[19.7,68.6]],"o":[[0,0],[2.8,0],[1.8,-1.6],[0,0],[0,0],[0,0],[-1.9,0],[-1.1,0.8],[0,0],[0,1.4],[1.1,0.9],[0,0]]}}},{"ty":"fl","c":{"a":0,"k":[1,1,1]},"o":{"a":0,"k":100}}]},{"ind":242,"ty":3,"ks":{"p":{"a":0,"k":[-3,-34]}},"ip":0,"op":412,"st":0}]},{"id":"249","layers":[{"ind":248,"ty":4,"parent":247,"ks":{},"ip":0,"op":412,"st":0,"shapes":[{"ty":"sh","ks":{"a":0,"k":{"c":true,"i":[[0,0],[0,0],[0,0],[0,0],[0,0]],"v":[[15.7,75.7],[5.6,75.7],[5.6,19.7],[15.7,19.7],[15.7,75.7]],"o":[[0,0],[0,0],[0,0],[0,0],[0,0]]}}},{"ty":"fl","c":{"a":0,"k":[1,1,1]},"o":{"a":0,"k":100}}]},{"ind":247,"ty":3,"ks":{"p":{"a":0,"k":[-5,-19]}},"ip":0,"op":412,"st":0}]},{"id":"254","layers":[{"ind":253,"ty":4,"parent":252,"ks":{},"ip":0,"op":412,"st":0,"shapes":[{"ty":"sh","ks":{"a":0,"k":{"c":true,"i":[[0,0],[0,0],[3.1,1.6],[1.8,3],[0,4.3],[0,0],[0,0],[-1.8,3],[-3.1,1.6],[-3.9,0],[0,0],[-3.1,-1.6],[-1.8,-3],[0,-4.3],[0,0],[0,0],[1.8,-3],[3.1,-1.6],[3.9,0]],"v":[[24.5,76.8],[24.5,76.8],[13.8,74.4],[6.4,67.4],[3.7,56.5],[3.7,56.5],[3.7,55.2],[6.4,44.2],[13.8,37.3],[24.5,34.9],[24.5,34.9],[35.1,37.3],[42.6,44.2],[45.3,55.2],[45.3,55.2],[45.3,56.5],[42.6,67.4],[35.1,74.4],[24.5,76.8]],"o":[[0,0],[-3.9,0],[-3.1,-1.6],[-1.8,-3],[0,0],[0,0],[0,-4.3],[1.8,-3],[3.1,-1.6],[0,0],[3.9,0],[3.1,1.6],[1.8,3],[0,0],[0,0],[0,4.3],[-1.8,3],[-3.1,1.6],[0,0]]}}},{"ty":"sh","ks":{"a":0,"k":{"c":true,"i":[[0,0],[0,0],[-2,2],[0,3.7],[0,0],[0,0],[2,2],[3.1,0],[0,0],[2,-2],[0,-3.7],[0,0],[0,0],[-2,-2],[-3.1,0]],"v":[[24.5,67.8],[24.5,67.8],[32.2,64.8],[35.2,56.2],[35.2,56.2],[35.2,55.4],[32.2,46.8],[24.5,43.8],[24.5,43.8],[16.8,46.8],[13.8,55.4],[13.8,55.4],[13.8,56.2],[16.8,64.8],[24.5,67.8]],"o":[[0,0],[3.1,0],[2,-2],[0,0],[0,0],[0,-3.7],[-2,-2],[0,0],[-3.1,0],[-2,2],[0,0],[0,0],[0,3.7],[2,2],[0,0]]}}},{"ty":"fl","c":{"a":0,"k":[1,1,1]},"o":{"a":0,"k":100}}]},{"ind":252,"ty":3,"ks":{"p":{"a":0,"k":[-3,-34]}},"ip":0,"op":412,"st":0}]},{"id":"259","layers":[{"ind":258,"ty":4,"parent":257,"ks":{},"ip":0,"op":412,"st":0,"shapes":[{"ty":"sh","ks":{"a":0,"k":{"c":true,"i":[[0,0],[0,0],[0,0],[0,0],[0,0],[0,0],[-1.9,1.2],[-3.6,0],[0,0],[-2.7,-1.6],[-1.7,-3],[0,-4.3],[0,0],[0,0],[1.7,-3],[2.7,-1.6],[3.2,0],[0,0],[1.6,0.6],[1,0.9],[0.6,0.9],[0,0],[0,0],[0,0]],"v":[[15.7,91.7],[5.6,91.7],[5.6,36],[15.5,36],[15.5,40.8],[17,40.8],[21.2,36.7],[29.4,34.9],[29.4,34.9],[38.3,37.2],[44.9,44.2],[47.4,55.2],[47.4,55.2],[47.4,56.5],[44.9,67.5],[38.3,74.4],[29.4,76.8],[29.4,76.8],[23.4,76],[19.5,73.8],[17.1,71.1],[17.1,71.1],[15.7,71.1],[15.7,91.7]],"o":[[0,0],[0,0],[0,0],[0,0],[0,0],[0.9,-1.5],[1.9,-1.2],[0,0],[3.2,0],[2.7,1.6],[1.7,3],[0,0],[0,0],[0,4.3],[-1.7,3],[-2.7,1.6],[0,0],[-2.4,0],[-1.6,-0.6],[-1,-0.9],[0,0],[0,0],[0,0],[0,0]]}}},{"ty":"sh","ks":{"a":0,"k":{"c":true,"i":[[0,0],[0,0],[-2.1,2],[0,3.8],[0,0],[0,0],[2.1,2],[3.1,0],[0,0],[2.1,-2],[0,-3.8],[0,0],[0,0],[-2.1,-2],[-3.1,0]],"v":[[26.4,68],[26.4,68],[34.2,65],[37.3,56.2],[37.3,56.2],[37.3,55.4],[34.2,46.7],[26.4,43.7],[26.4,43.7],[18.6,46.7],[15.5,55.4],[15.5,55.4],[15.5,56.2],[18.6,65],[26.4,68]],"o":[[0,0],[3.1,0],[2.1,-2],[0,0],[0,0],[0,-3.8],[-2.1,-2],[0,0],[-3.1,0],[-2.1,2],[0,0],[0,0],[0,3.8],[2.1,2],[0,0]]}}},{"ty":"fl","c":{"a":0,"k":[1,1,1]},"o":{"a":0,"k":100}}]},{"ind":257,"ty":3,"ks":{"p":{"a":0,"k":[-5,-34]}},"ip":0,"op":412,"st":0}]},{"id":"264","layers":[{"ind":263,"ty":4,"parent":262,"ks":{},"ip":0,"op":412,"st":0,"shapes":[{"ty":"sh","ks":{"a":0,"k":{"c":true,"i":[[0,0],[0,0],[3,1.7],[1.7,3.1],[0,4.2],[0,0],[0,0],[-1.7,3.1],[-3,1.7],[-3.9,0],[0,0],[-2.9,-1.7],[-1.6,-3.1],[0,-4.1],[0,0],[0,0],[0,0],[-1.9,-1.7],[-2.8,0],[0,0],[-1.3,1.2],[-0.7,1.5],[0,0],[0,0],[1.4,-1.6],[2.3,-1.1],[3.6,0]],"v":[[23.7,76.8],[23.7,76.8],[13.2,74.3],[6.2,67.2],[3.7,56.3],[3.7,56.3],[3.7,55.4],[6.2,44.5],[13.1,37.4],[23.5,34.9],[23.5,34.9],[33.7,37.5],[40.4,44.7],[42.8,55.4],[42.8,55.4],[42.8,58.8],[13.9,58.8],[17,65.4],[24,68],[24,68],[30.2,66.2],[33.3,62.1],[33.3,62.1],[41.5,66.4],[38.3,70.9],[32.6,75.1],[23.7,76.8]],"o":[[0,0],[-3.9,0],[-3,-1.7],[-1.7,-3.1],[0,0],[0,0],[0,-4.2],[1.7,-3.1],[3,-1.7],[0,0],[3.9,0],[2.9,1.7],[1.6,3.1],[0,0],[0,0],[0,0],[0.1,2.7],[1.9,1.7],[0,0],[2.8,0],[1.3,-1.2],[0,0],[0,0],[-0.7,1.4],[-1.4,1.6],[-2.3,1.1],[0,0]]}}},{"ty":"sh","ks":{"a":0,"k":{"c":true,"i":[[0,0],[0,0],[0,0],[1.6,1.4],[2.6,0],[0,0],[1.6,-1.4],[0.4,-2.3]],"v":[[14,51.3],[14,51.3],[32.6,51.3],[29.8,45.8],[23.4,43.7],[23.4,43.7],[17,45.8],[14,51.3]],"o":[[0,0],[0,0],[-0.2,-2.3],[-1.6,-1.4],[0,0],[-2.7,0],[-1.6,1.4],[0,0]]}}},{"ty":"fl","c":{"a":0,"k":[1,1,1]},"o":{"a":0,"k":100}}]},{"ind":262,"ty":3,"ks":{"p":{"a":0,"k":[-3,-34]}},"ip":0,"op":412,"st":0}]},{"id":"269","layers":[{"ind":268,"ty":4,"parent":267,"ks":{},"ip":0,"op":412,"st":0,"shapes":[{"ty":"sh","ks":{"a":0,"k":{"c":true,"i":[[0,0],[0,0],[2.7,1.6],[1.7,3],[0,4.3],[0,0],[0,0],[-1.7,3],[-2.7,1.6],[-3.2,0],[0,0],[-1.6,-0.6],[-1,-0.9],[-0.5,-1],[0,0],[0,0],[0,0],[0,0],[0,0],[0,0],[0,0],[0,0],[1.9,-1.2],[3.6,0]],"v":[[21.6,76.8],[21.6,76.8],[12.8,74.4],[6.2,67.5],[3.7,56.5],[3.7,56.5],[3.7,55.2],[6.2,44.2],[12.7,37.2],[21.6,34.9],[21.6,34.9],[27.6,35.7],[31.6,37.8],[33.9,40.6],[33.9,40.6],[35.4,40.6],[35.4,19.7],[45.4,19.7],[45.4,75.7],[35.5,75.7],[35.5,70.9],[34.1,70.9],[29.9,75],[21.6,76.8]],"o":[[0,0],[-3.1,0],[-2.7,-1.6],[-1.7,-3],[0,0],[0,0],[0,-4.3],[1.7,-3],[2.7,-1.6],[0,0],[2.4,0],[1.6,0.6],[1,0.9],[0,0],[0,0],[0,0],[0,0],[0,0],[0,0],[0,0],[0,0],[-0.9,1.5],[-1.9,1.2],[0,0]]}}},{"ty":"sh","ks":{"a":0,"k":{"c":true,"i":[[0,0],[0,0],[-2.1,2],[0,3.8],[0,0],[0,0],[2.1,2],[3.1,0],[0,0],[2.1,-2],[0,-3.8],[0,0],[0,0],[-2.1,-2],[-3.1,0]],"v":[[24.6,68],[24.6,68],[32.4,65],[35.5,56.2],[35.5,56.2],[35.5,55.4],[32.4,46.7],[24.6,43.7],[24.6,43.7],[16.9,46.7],[13.8,55.4],[13.8,55.4],[13.8,56.2],[16.9,65],[24.6,68]],"o":[[0,0],[3.1,0],[2.1,-2],[0,0],[0,0],[0,-3.8],[-2.1,-2],[0,0],[-3.1,0],[-2.1,2],[0,0],[0,0],[0,3.8],[2.1,2],[0,0]]}}},{"ty":"fl","c":{"a":0,"k":[1,1,1]},"o":{"a":0,"k":100}}]},{"ind":267,"ty":3,"ks":{"p":{"a":0,"k":[-3,-19]}},"ip":0,"op":412,"st":0}]},{"id":"274","layers":[{"ind":273,"ty":4,"parent":272,"ks":{},"ip":0,"op":412,"st":0,"shapes":[{"ty":"sh","ks":{"a":0,"k":{"c":true,"i":[[0,0],[0,0],[3.1,1.6],[1.8,3],[0,4.3],[0,0],[0,0],[-1.8,3],[-3.1,1.6],[-3.9,0],[0,0],[-3.1,-1.6],[-1.8,-3],[0,-4.3],[0,0],[0,0],[1.8,-3],[3.1,-1.6],[3.9,0]],"v":[[24.5,76.8],[24.5,76.8],[13.8,74.4],[6.4,67.4],[3.7,56.5],[3.7,56.5],[3.7,55.2],[6.4,44.2],[13.8,37.3],[24.5,34.9],[24.5,34.9],[35.1,37.3],[42.6,44.2],[45.3,55.2],[45.3,55.2],[45.3,56.5],[42.6,67.4],[35.1,74.4],[24.5,76.8]],"o":[[0,0],[-3.9,0],[-3.1,-1.6],[-1.8,-3],[0,0],[0,0],[0,-4.3],[1.8,-3],[3.1,-1.6],[0,0],[3.9,0],[3.1,1.6],[1.8,3],[0,0],[0,0],[0,4.3],[-1.8,3],[-3.1,1.6],[0,0]]}}},{"ty":"sh","ks":{"a":0,"k":{"c":true,"i":[[0,0],[0,0],[-2,2],[0,3.7],[0,0],[0,0],[2,2],[3.1,0],[0,0],[2,-2],[0,-3.7],[0,0],[0,0],[-2,-2],[-3.1,0]],"v":[[24.5,67.8],[24.5,67.8],[32.2,64.8],[35.2,56.2],[35.2,56.2],[35.2,55.4],[32.2,46.8],[24.5,43.8],[24.5,43.8],[16.8,46.8],[13.8,55.4],[13.8,55.4],[13.8,56.2],[16.8,64.8],[24.5,67.8]],"o":[[0,0],[3.1,0],[2,-2],[0,0],[0,0],[0,-3.7],[-2,-2],[0,0],[-3.1,0],[-2,2],[0,0],[0,0],[0,3.7],[2,2],[0,0]]}}},{"ty":"fl","c":{"a":0,"k":[1,1,1]},"o":{"a":0,"k":100}}]},{"ind":272,"ty":3,"ks":{"p":{"a":0,"k":[-3,-34]}},"ip":0,"op":412,"st":0}]},{"id":"279","layers":[{"ind":278,"ty":4,"parent":277,"ks":{},"ip":0,"op":412,"st":0,"shapes":[{"ty":"sh","ks":{"a":0,"k":{"c":true,"i":[[0,0],[0,0],[3.1,1.6],[1.8,3],[0,4.3],[0,0],[0,0],[-1.8,3],[-3.1,1.6],[-3.8,0],[0,0],[-2.7,-1.3],[-1.7,-2.3],[-0.5,-2.9],[0,0],[0,0],[0.7,1.3],[1.4,0.7],[2,0],[0,0],[1.6,-0.9],[0.9,-1.7],[0,-2.5],[0,0],[0,0],[-0.9,-1.7],[-1.6,-0.9],[-2,0],[0,0],[-1.6,1.6],[-0.4,2.6],[0,0],[0,0],[1.7,-2.3],[2.7,-1.3],[3.8,0]],"v":[[24.2,76.8],[24.2,76.8],[13.8,74.4],[6.4,67.4],[3.7,56.4],[3.7,56.4],[3.7,55.3],[6.4,44.2],[13.8,37.3],[24.2,34.9],[24.2,34.9],[34,36.9],[40.6,42.4],[43.9,50.2],[43.9,50.2],[34.2,52.3],[32.7,48],[29.6,45],[24.5,43.8],[24.5,43.8],[19,45.2],[15.2,49.1],[13.8,55.4],[13.8,55.4],[13.8,56.2],[15.2,62.6],[19,66.5],[24.5,67.8],[24.5,67.8],[31.4,65.5],[34.4,59.3],[34.4,59.3],[44.2,61.6],[40.6,69.3],[34,74.8],[24.2,76.8]],"o":[[0,0],[-3.8,0],[-3.1,-1.6],[-1.8,-3],[0,0],[0,0],[0,-4.3],[1.8,-3],[3.1,-1.6],[0,0],[3.8,0],[2.7,1.3],[1.7,2.3],[0,0],[0,0],[-0.2,-1.6],[-0.7,-1.3],[-1.4,-0.7],[0,0],[-2,0],[-1.6,0.9],[-0.9,1.7],[0,0],[0,0],[0,2.5],[0.9,1.7],[1.6,0.9],[0,0],[3,0],[1.6,-1.6],[0,0],[0,0],[-0.7,2.8],[-1.7,2.3],[-2.7,1.3],[0,0]]}}},{"ty":"fl","c":{"a":0,"k":[1,1,1]},"o":{"a":0,"k":100}}]},{"ind":277,"ty":3,"ks":{"p":{"a":0,"k":[-3,-34]}},"ip":0,"op":412,"st":0}]}],"fr":60,"h":720,"ip":0,"layers":[{"ind":183,"ty":0,"td":1,"parent":2,"ks":{"a":{"a":0,"k":[68,66]}},"w":339,"h":330,"ip":0,"op":412,"st":0,"refId":"181"},{"ind":172,"ty":0,"tt":1,"parent":2,"ks":{"a":{"a":0,"k":[15,15]}},"w":192,"h":163,"ip":0,"op":412,"st":0,"refId":"170"},{"ind":2,"ty":3,"parent":1,"ks":{"p":{"a":0,"k":[573,294]}},"ip":0,"op":412,"st":0},{"ind":203,"ty":0,"td":1,"parent":184,"ks":{"a":{"a":0,"k":[61,61]}},"w":726,"h":730,"ip":0,"op":412,"st":0,"refId":"201"},{"ind":192,"ty":0,"tt":1,"parent":184,"ks":{"a":{"a":0,"k":[60.5,60.5]},"o":{"a":1,"k":[{"t":0,"s":[0],"h":1},{"t":175.86,"s":[0],"i":{"x":1,"y":1},"o":{"x":0,"y":0}},{"t":192.84,"s":[100],"h":1},{"t":411,"s":[100],"h":1}]},"p":{"a":0,"k":[60.5,60.5]},"s":{"a":1,"k":[{"t":0,"s":[120,120],"i":{"x":[1,1],"y":[1,1]},"o":{"x":[0,0],"y":[0,0]}},{"t":175.86,"s":[120,120],"i":{"x":[0,0],"y":[1,1]},"o":{"x":[0.5,0.5],"y":[0,0]}},{"t":219,"s":[100,100],"i":{"x":[1,1],"y":[1,1]},"o":{"x":[0,0],"y":[0,0]}},{"t":411,"s":[100,100],"h":1}]}},"w":564,"h":568,"ip":0,"op":412,"st":0,"refId":"190"},{"ind":184,"ty":3,"parent":1,"ks":{"p":{"a":1,"k":[{"t":0,"s":[580,300],"i":{"x":[1,1],"y":[1,1]},"o":{"x":[0,0],"y":[0,0]}},{"t":219,"s":[580,300],"i":{"x":[0.25,1],"y":[1,1]},"o":{"x":[0.25,0],"y":[0.1,0]}},{"t":252.96,"s":[310,300],"i":{"x":[1,1],"y":[1,1]},"o":{"x":[0,0],"y":[0,0]}},{"t":411,"s":[310,300],"h":1}]}},"ip":0,"op":412,"st":0},{"ind":211,"ty":0,"parent":206,"ks":{"a":{"a":0,"k":[-3,-34]},"o":{"a":1,"k":[{"t":0,"s":[0],"h":1},{"t":252.930156,"s":[0],"i":{"x":1,"y":1},"o":{"x":0,"y":0}},{"t":304.86,"s":[100],"h":1},{"t":411,"s":[100],"h":1}]},"p":{"a":1,"k":[{"t":0,"s":[592.4,0],"i":{"x":[1,1],"y":[1,1]},"o":{"x":[0,0],"y":[0,0]}},{"t":252.93,"s":[592.4,0],"i":{"x":[0.25,1],"y":[1,1]},"o":{"x":[0.25,0],"y":[0.1,0]}},{"t":304.86,"s":[544.4,0],"i":{"x":[1,1],"y":[1,1]},"o":{"x":[0,0],"y":[0,0]}},{"t":411,"s":[544.4,0],"h":1}]}},"w":43,"h":43,"ip":0,"op":412,"st":0,"refId":"209"},{"ind":216,"ty":0,"parent":206,"ks":{"a":{"a":0,"k":[-4,-18]},"o":{"a":1,"k":[{"t":0,"s":[0],"h":1},{"t":250.165108,"s":[0],"i":{"x":1,"y":1},"o":{"x":0,"y":0}},{"t":276.183529,"s":[100],"h":1},{"t":411,"s":[100],"h":1}]},"p":{"a":1,"k":[{"t":0,"s":[571.12,0],"i":{"x":[1,1],"y":[1,1]},"o":{"x":[0,0],"y":[0,0]}},{"t":250.164,"s":[571.12,0],"i":{"x":[0.25,1],"y":[1,1]},"o":{"x":[0.25,0],"y":[0.1,0]}},{"t":276.186,"s":[523.12,0],"i":{"x":[1,1],"y":[1,1]},"o":{"x":[0,0],"y":[0,0]}},{"t":411,"s":[523.12,0],"h":1}]}},"w":14,"h":58,"ip":0,"op":412,"st":0,"refId":"214"},{"ind":221,"ty":0,"parent":206,"ks":{"a":{"a":0,"k":[-4,-61]},"o":{"a":1,"k":[{"t":0,"s":[0],"h":1},{"t":247.654496,"s":[0],"i":{"x":1,"y":1},"o":{"x":0,"y":0}},{"t":268.729911,"s":[100],"h":1},{"t":411,"s":[100],"h":1}]},"p":{"a":1,"k":[{"t":0,"s":[547.28,0],"i":{"x":[1,1],"y":[1,1]},"o":{"x":[0,0],"y":[0,0]}},{"t":247.656,"s":[547.28,0],"i":{"x":[0.25,1],"y":[1,1]},"o":{"x":[0.25,0],"y":[0.1,0]}},{"t":268.728,"s":[499.28,0],"i":{"x":[1,1],"y":[1,1]},"o":{"x":[0,0],"y":[0,0]}},{"t":411,"s":[499.28,0],"h":1}]}},"w":16,"h":16,"ip":0,"op":412,"st":0,"refId":"219"},{"ind":226,"ty":0,"parent":206,"ks":{"a":{"a":0,"k":[-5,-36]},"o":{"a":1,"k":[{"t":0,"s":[0],"h":1},{"t":245.346801,"s":[0],"i":{"x":1,"y":1},"o":{"x":0,"y":0}},{"t":263.501372,"s":[100],"h":1},{"t":411,"s":[100],"h":1}]},"p":{"a":1,"k":[{"t":0,"s":[498,0],"i":{"x":[1,1],"y":[1,1]},"o":{"x":[0,0],"y":[0,0]}},{"t":245.346,"s":[498,0],"i":{"x":[0.25,1],"y":[1,1]},"o":{"x":[0.25,0],"y":[0.1,0]}},{"t":263.502,"s":[450,0],"i":{"x":[1,1],"y":[1,1]},"o":{"x":[0,0],"y":[0,0]}},{"t":411,"s":[450,0],"h":1}]}},"w":39,"h":56,"ip":0,"op":412,"st":0,"refId":"224"},{"ind":231,"ty":0,"parent":206,"ks":{"a":{"a":0,"k":[-2,-23]},"o":{"a":1,"k":[{"t":0,"s":[0],"h":1},{"t":243.205409,"s":[0],"i":{"x":1,"y":1},"o":{"x":0,"y":0}},{"t":259.33894,"s":[100],"h":1},{"t":411,"s":[100],"h":1}]},"p":{"a":1,"k":[{"t":0,"s":[461.52,0],"i":{"x":[1,1],"y":[1,1]},"o":{"x":[0,0],"y":[0,0]}},{"t":243.204,"s":[461.52,0],"i":{"x":[0.25,1],"y":[1,1]},"o":{"x":[0.25,0],"y":[0.1,0]}},{"t":259.338,"s":[413.52,0],"i":{"x":[1,1],"y":[1,1]},"o":{"x":[0,0],"y":[0,0]}},{"t":411,"s":[413.52,0],"h":1}]}},"w":31,"h":53,"ip":0,"op":412,"st":0,"refId":"229"},{"ind":236,"ty":0,"parent":206,"ks":{"a":{"a":0,"k":[-4,-18]},"o":{"a":1,"k":[{"t":0,"s":[0],"h":1},{"t":241.203252,"s":[0],"i":{"x":1,"y":1},"o":{"x":0,"y":0}},{"t":255.823924,"s":[100],"h":1},{"t":411,"s":[100],"h":1}]},"p":{"a":1,"k":[{"t":0,"s":[440.24,0],"i":{"x":[1,1],"y":[1,1]},"o":{"x":[0,0],"y":[0,0]}},{"t":241.206,"s":[440.24,0],"i":{"x":[0.25,1],"y":[1,1]},"o":{"x":[0.25,0],"y":[0.1,0]}},{"t":255.822,"s":[392.24,0],"i":{"x":[1,1],"y":[1,1]},"o":{"x":[0,0],"y":[0,0]}},{"t":411,"s":[392.24,0],"h":1}]}},"w":14,"h":58,"ip":0,"op":412,"st":0,"refId":"234"},{"ind":241,"ty":0,"parent":206,"ks":{"a":{"a":0,"k":[-5,-35]},"o":{"a":1,"k":[{"t":0,"s":[0],"h":1},{"t":239.31969,"s":[0],"i":{"x":1,"y":1},"o":{"x":0,"y":0}},{"t":252.751394,"s":[100],"h":1},{"t":411,"s":[100],"h":1}]},"p":{"a":1,"k":[{"t":0,"s":[408.56,0],"i":{"x":[1,1],"y":[1,1]},"o":{"x":[0,0],"y":[0,0]}},{"t":239.322,"s":[408.56,0],"i":{"x":[0.25,1],"y":[1,1]},"o":{"x":[0.25,0],"y":[0.1,0]}},{"t":252.75,"s":[360.56,0],"i":{"x":[1,1],"y":[1,1]},"o":{"x":[0,0],"y":[0,0]}},{"t":411,"s":[360.56,0],"h":1}]}},"w":25,"h":41,"ip":0,"op":412,"st":0,"refId":"239"},{"ind":246,"ty":0,"parent":206,"ks":{"a":{"a":0,"k":[-3,-34]},"o":{"a":1,"k":[{"t":0,"s":[0],"h":1},{"t":237.538583,"s":[0],"i":{"x":1,"y":1},"o":{"x":0,"y":0}},{"t":250.003885,"s":[100],"h":1},{"t":411,"s":[100],"h":1}]},"p":{"a":1,"k":[{"t":0,"s":[362.32,0],"i":{"x":[1,1],"y":[1,1]},"o":{"x":[0,0],"y":[0,0]}},{"t":237.54,"s":[362.32,0],"i":{"x":[0.25,1],"y":[1,1]},"o":{"x":[0.25,0],"y":[0.1,0]}},{"t":250.002,"s":[314.32,0],"i":{"x":[1,1],"y":[1,1]},"o":{"x":[0,0],"y":[0,0]}},{"t":411,"s":[314.32,0],"h":1}]}},"w":42,"h":43,"ip":0,"op":412,"st":0,"refId":"244"},{"ind":251,"ty":0,"parent":206,"ks":{"a":{"a":0,"k":[-5,-19]},"o":{"a":1,"k":[{"t":0,"s":[0],"h":1},{"t":235.847041,"s":[0],"i":{"x":1,"y":1},"o":{"x":0,"y":0}},{"t":247.507058,"s":[100],"h":1},{"t":411,"s":[100],"h":1}]},"p":{"a":1,"k":[{"t":0,"s":[341.04,0],"i":{"x":[1,1],"y":[1,1]},"o":{"x":[0,0],"y":[0,0]}},{"t":235.848,"s":[341.04,0],"i":{"x":[0.25,1],"y":[1,1]},"o":{"x":[0.25,0],"y":[0.1,0]}},{"t":247.506,"s":[293.04,0],"i":{"x":[1,1],"y":[1,1]},"o":{"x":[0,0],"y":[0,0]}},{"t":411,"s":[293.04,0],"h":1}]}},"w":11,"h":57,"ip":0,"op":412,"st":0,"refId":"249"},{"ind":256,"ty":0,"parent":206,"ks":{"a":{"a":0,"k":[-3,-34]},"o":{"a":1,"k":[{"t":0,"s":[0],"h":1},{"t":234.234588,"s":[0],"i":{"x":1,"y":1},"o":{"x":0,"y":0}},{"t":245.210537,"s":[100],"h":1},{"t":411,"s":[100],"h":1}]},"p":{"a":1,"k":[{"t":0,"s":[292.08,0],"i":{"x":[1,1],"y":[1,1]},"o":{"x":[0,0],"y":[0,0]}},{"t":234.234,"s":[292.08,0],"i":{"x":[0.25,1],"y":[1,1]},"o":{"x":[0.25,0],"y":[0.1,0]}},{"t":245.208,"s":[244.08,0],"i":{"x":[1,1],"y":[1,1]},"o":{"x":[0,0],"y":[0,0]}},{"t":411,"s":[244.08,0],"h":1}]}},"w":43,"h":43,"ip":0,"op":412,"st":0,"refId":"254"},{"ind":261,"ty":0,"parent":206,"ks":{"a":{"a":0,"k":[-5,-34]},"o":{"a":1,"k":[{"t":0,"s":[0],"h":1},{"t":232.692582,"s":[0],"i":{"x":1,"y":1},"o":{"x":0,"y":0}},{"t":243.078416,"s":[100],"h":1},{"t":411,"s":[100],"h":1}]},"p":{"a":1,"k":[{"t":0,"s":[241.04,0],"i":{"x":[1,1],"y":[1,1]},"o":{"x":[0,0],"y":[0,0]}},{"t":232.692,"s":[241.04,0],"i":{"x":[0.25,1],"y":[1,1]},"o":{"x":[0.25,0],"y":[0.1,0]}},{"t":243.078,"s":[193.04,0],"i":{"x":[1,1],"y":[1,1]},"o":{"x":[0,0],"y":[0,0]}},{"t":411,"s":[193.04,0],"h":1}]}},"w":43,"h":58,"ip":0,"op":412,"st":0,"refId":"259"},{"ind":266,"ty":0,"parent":206,"ks":{"a":{"a":0,"k":[-3,-34]},"o":{"a":1,"k":[{"t":0,"s":[0],"h":1},{"t":231.213798,"s":[0],"i":{"x":1,"y":1},"o":{"x":0,"y":0}},{"t":241.0841,"s":[100],"h":1},{"t":411,"s":[100],"h":1}]},"p":{"a":1,"k":[{"t":0,"s":[194.88,0],"i":{"x":[1,1],"y":[1,1]},"o":{"x":[0,0],"y":[0,0]}},{"t":231.216,"s":[194.88,0],"i":{"x":[0.25,1],"y":[1,1]},"o":{"x":[0.25,0],"y":[0.1,0]}},{"t":241.086,"s":[146.88,0],"i":{"x":[1,1],"y":[1,1]},"o":{"x":[0,0],"y":[0,0]}},{"t":411,"s":[146.88,0],"h":1}]}},"w":40,"h":43,"ip":0,"op":412,"st":0,"refId":"264"},{"ind":271,"ty":0,"parent":206,"ks":{"a":{"a":0,"k":[-3,-19]},"o":{"a":1,"k":[{"t":0,"s":[0],"h":1},{"t":229.792129,"s":[0],"i":{"x":1,"y":1},"o":{"x":0,"y":0}},{"t":239.207271,"s":[100],"h":1},{"t":411,"s":[100],"h":1}]},"p":{"a":1,"k":[{"t":0,"s":[143.84,0],"i":{"x":[1,1],"y":[1,1]},"o":{"x":[0,0],"y":[0,0]}},{"t":229.794,"s":[143.84,0],"i":{"x":[0.25,1],"y":[1,1]},"o":{"x":[0.25,0],"y":[0.1,0]}},{"t":239.208,"s":[95.84,0],"i":{"x":[1,1],"y":[1,1]},"o":{"x":[0,0],"y":[0,0]}},{"t":411,"s":[95.84,0],"h":1}]}},"w":43,"h":58,"ip":0,"op":412,"st":0,"refId":"269"},{"ind":276,"ty":0,"parent":206,"ks":{"a":{"a":0,"k":[-3,-34]},"o":{"a":1,"k":[{"t":0,"s":[0],"h":1},{"t":228.42236,"s":[0],"i":{"x":1,"y":1},"o":{"x":0,"y":0}},{"t":237.432019,"s":[100],"h":1},{"t":411,"s":[100],"h":1}]},"p":{"a":1,"k":[{"t":0,"s":[94.88,0],"i":{"x":[1,1],"y":[1,1]},"o":{"x":[0,0],"y":[0,0]}},{"t":228.42,"s":[94.88,0],"i":{"x":[0.25,1],"y":[1,1]},"o":{"x":[0.25,0],"y":[0.1,0]}},{"t":237.432,"s":[46.88,0],"i":{"x":[1,1],"y":[1,1]},"o":{"x":[0,0],"y":[0,0]}},{"t":411,"s":[46.88,0],"h":1}]}},"w":43,"h":43,"ip":0,"op":412,"st":0,"refId":"274"},{"ind":281,"ty":0,"parent":206,"ks":{"a":{"a":0,"k":[-3,-34]},"o":{"a":1,"k":[{"t":0,"s":[0],"h":1},{"t":227.1,"s":[0],"i":{"x":1,"y":1},"o":{"x":0,"y":0}},{"t":235.745625,"s":[100],"h":1},{"t":411,"s":[100],"h":1}]},"p":{"a":1,"k":[{"t":0,"s":[48,0],"i":{"x":[1,1],"y":[1,1]},"o":{"x":[0,0],"y":[0,0]}},{"t":227.1,"s":[48,0],"i":{"x":[0.25,1],"y":[1,1]},"o":{"x":[0.25,0],"y":[0.1,0]}},{"t":235.746,"s":[0,0],"i":{"x":[1,1],"y":[1,1]},"o":{"x":[0,0],"y":[0,0]}},{"t":411,"s":[0,0],"h":1}]}},"w":42,"h":43,"ip":0,"op":412,"st":0,"refId":"279"},{"ind":206,"ty":3,"parent":205,"ks":{},"ip":0,"op":412,"st":0},{"ind":205,"ty":3,"parent":204,"ks":{},"ip":0,"op":412,"st":0},{"ind":204,"ty":3,"parent":1,"ks":{"p":{"a":1,"k":[{"t":0,"s":[684,312],"i":{"x":[1,1],"y":[1,1]},"o":{"x":[0,0],"y":[0,0]}},{"t":218.34,"s":[684,312],"i":{"x":[0.25,1],"y":[1,1]},"o":{"x":[0.25,0],"y":[0.1,0]}},{"t":252.3,"s":[458,312],"i":{"x":[1,1],"y":[1,1]},"o":{"x":[0,0],"y":[0,0]}},{"t":411,"s":[458,312],"h":1}]}},"ip":0,"op":412,"st":0},{"ind":1,"ty":3,"parent":0,"ks":{},"ip":0,"op":412,"st":0},{"ind":282,"ty":4,"parent":0,"ks":{},"ip":0,"op":412,"st":0,"shapes":[{"ty":"rc","p":{"a":0,"k":[640,360]},"r":{"a":0,"k":0},"s":{"a":0,"k":[1280,720]}},{"ty":"fl","c":{"a":0,"k":[0,0,0]},"o":{"a":0,"k":100}}]},{"ind":0,"ty":3,"ks":{},"ip":0,"op":412,"st":0}],"meta":{"g":"https://jitter.video"},"op":411,"v":"5.7.4","w":1280}